{
    "$schema": "vscode://schemas/color-theme",
    "type": "dark",
    "colors": {
        "actionBar.toggledBackground": "#111111fe",
        "activityBar.activeBackground": "#0d0d0dfe",
        "activityBar.activeBorder": "#e9e9e9be",
        "activityBar.activeFocusBorder": "#01010100",
        "activityBar.background": "#0d0d0dfe",
        "activityBar.border": "#01010100",
        "activityBar.dropBorder": "#000000fe",
        "activityBar.foreground": "#ddddddbe",
        "activityBar.inactiveForeground": "#b9b9b947",
        "activityBarBadge.background": "#959595be",
        "activityBarBadge.foreground": "#0d0d0dfe",
        "badge.background": "#a1a1a1be",
        "badge.foreground": "#0d0d0dfe",
        "banner.background": "#111111fe",
        "banner.foreground": "#c9c9c9be",
        "banner.iconForeground": "#8967bafe",
        "breadcrumb.activeSelectionForeground": "#88acdbca",
        "breadcrumb.background": "#111111fe",
        "breadcrumb.focusForeground": "#d9d9d9be",
        "breadcrumb.foreground": "#e9e9e9be",
        "breadcrumbPicker.background": "#111111fe",
        "button.background": "#252525ce",
        "button.border": "#01010100",
        "button.foreground": "#c9c9c9be",
        "button.hoverBackground": "#8181811e",
        "button.secondaryBackground": "#111111fe",
        "button.secondaryForeground": "#bdbdbdbe",
        "button.secondaryHoverBackground": "#111111fe",
        "button.separator": "#c2bf6ff0",
        "charts.blue": "#6767ffa9",
        "charts.foreground": "#bdbdbdbe",
        "charts.green": "#004000cb",
        "charts.lines": "#151515f5",
        "charts.orange": "#ffba22ce",
        "charts.purple": "#670067a1",
        "charts.red": "#400000cb",
        "charts.yellow": "#e6e600ce",
        "chat.requestBorder": "#000000fe",
        "chat.slashCommandBackground": "#111111fe",
        "chat.slashCommandForeground": "#bdbdbdbe",
        "checkbox.background": "#111111fe",
        "checkbox.border": "#999999be",
        "checkbox.foreground": "#c5c5c5be",
        "checkbox.selectBackground": "#85858541",
        "checkbox.selectBorder": "#959595be",
        "commandCenter.activeBackground": "#7397c641",
        "commandCenter.activeBorder": "#999999be",
        "commandCenter.activeForeground": "#c1c1c1be",
        "commandCenter.background": "#111111fe",
        "commandCenter.border": "#000000fe",
        "commandCenter.foreground": "#bdbdbdbe",
        "commandCenter.inactiveBorder": "#919191be",
        "commandCenter.inactiveForeground": "#a5a5a542",
        "commentsView.resolvedIcon": "#00cc00cb",
        "commentsView.unresolvedIcon": "#00cc00cb",
        "contrastActiveBorder": "#01010100",
        "contrastBorder": "#01010100",
        "debugConsole.errorForeground": "#cc00ffce",
        "debugConsole.infoForeground": "#c5c5c5be",
        "debugConsole.sourceForeground": "#cdcdcdbe",
        "debugConsole.warningForeground": "#e6e600ce",
        "debugConsoleInputIcon.foreground": "#959595be",
        "debugExceptionWidget.background": "#670067a8",
        "debugExceptionWidget.border": "#000000fe",
        "debugIcon.breakpointCurrentStackframeForeground": "#a9a656fe",
        "debugIcon.breakpointDisabledForeground": "#c7c474fe",
        "debugIcon.breakpointForeground": "#d481bdfe",
        "debugIcon.breakpointStackframeForeground": "#8c6abdfe",
        "debugIcon.breakpointUnverifiedForeground": "#8addc1fe",
        "debugIcon.continueForeground": "#62b599fe",
        "debugIcon.disconnectForeground": "#8bcf7cfe",
        "debugIcon.pauseForeground": "#9b79ccfe",
        "debugIcon.restartForeground": "#c976b2fe",
        "debugIcon.startForeground": "#c97f76fe",
        "debugIcon.stepBackForeground": "#5bae92fe",
        "debugIcon.stepIntoForeground": "#6b8fbefe",
        "debugIcon.stepOutForeground": "#d17ebafe",
        "debugIcon.stepOverForeground": "#90d481fe",
        "debugIcon.stopForeground": "#8db1e0fe",
        "debugTokenExpression.boolean": "#97db88fb",
        "debugTokenExpression.error": "#8db1e0f3",
        "debugTokenExpression.name": "#a482d5fe",
        "debugTokenExpression.number": "#d0cd7df6",
        "debugTokenExpression.string": "#7da1d0f6",
        "debugTokenExpression.value": "#d885c1f1",
        "debugToolBar.background": "#670067aa",
        "debugToolBar.border": "#000000fe",
        "debugView.exceptionLabelBackground": "#6700679d",
        "debugView.exceptionLabelForeground": "#d1d1d1be",
        "debugView.stateLabelBackground": "#670067b5",
        "debugView.stateLabelForeground": "#cdcdcdbe",
        "debugView.valueChangedHighlight": "#6d91c041",
        "descriptionForeground": "#d1d1d1be",
        "diffEditor.border": "#01010100",
        "diffEditor.diagonalFill": "#191919f5",
        "diffEditor.insertedLineBackground": "#9aff9a21",
        "diffEditor.insertedTextBackground": "#004000cb",
        "diffEditor.insertedTextBorder": "#01010100",
        "diffEditor.move.border": "#01010100",
        "diffEditor.moveActive.border": "#01010100",
        "diffEditor.removedLineBackground": "#ff9a9a21",
        "diffEditor.removedTextBackground": "#400000cb",
        "diffEditor.removedTextBorder": "#01010100",
        "diffEditor.unchangedCodeBackground": "#111111fe",
        "diffEditor.unchangedRegionBackground": "#111111fe",
        "diffEditor.unchangedRegionForeground": "#c9c9c9be",
        "diffEditorGutter.insertedLineBackground": "#004000cb",
        "diffEditorGutter.removedLineBackground": "#400000cb",
        "diffEditorOverview.insertedForeground": "#00cc00cb",
        "diffEditorOverview.removedForeground": "#ff6a6acb",
        "disabledForeground": "#c5c5c544",
        "dropdown.background": "#111111fe",
        "dropdown.border": "#a1a1a1be",
        "dropdown.foreground": "#b9b9b9be",
        "dropdown.listBackground": "#111111fe",
        "editor.background": "#111111fe",
        "editor.findMatchBackground": "#7195c441",
        "editor.findMatchBorder": "#70c3a741",
        "editor.findMatchHighlightBackground": "#9674c741",
        "editor.findMatchHighlightBorder": "#906ec141",
        "editor.findRangeHighlightBackground": "#89898941",
        "editor.findRangeHighlightBorder": "#9371c441",
        "editor.focusedStackFrameHighlightBackground": "#7498c741",
        "editor.foldBackground": "#7fc37041",
        "editor.foreground": "#cdcdcdbe",
        "editor.hoverHighlightBackground": "#8f6dc041",
        "editor.inactiveSelectionBackground": "#c1776e41",
        "editor.inlineValuesBackground": "#111111fe",
        "editor.inlineValuesForeground": "#d9d9d9be",
        "editor.lineHighlightBackground": "#8585851e",
        "editor.lineHighlightBorder": "#01010100",
        "editor.linkedEditingBackground": "#111111fe",
        "editor.rangeHighlightBackground": "#c5c27241",
        "editor.rangeHighlightBorder": "#9674c741",
        "editor.selectionBackground": "#7bbf6c41",
        "editor.selectionForeground": "#75c8acca",
        "editor.selectionHighlightBackground": "#89898941",
        "editor.selectionHighlightBorder": "#c4c17141",
        "editor.snippetFinalTabstopHighlightBackground": "#c87e7541",
        "editor.snippetFinalTabstopHighlightBorder": "#c0bd6d41",
        "editor.snippetTabstopHighlightBackground": "#c1be6e41",
        "editor.snippetTabstopHighlightBorder": "#79797941",
        "editor.stackFrameHighlightBackground": "#71717141",
        "editor.symbolHighlightBackground": "#6cbfa341",
        "editor.symbolHighlightBorder": "#c3c07041",
        "editor.wordHighlightBackground": "#74c7ab41",
        "editor.wordHighlightBorder": "#c471ad41",
        "editor.wordHighlightStrongBackground": "#bf756c41",
        "editor.wordHighlightStrongBorder": "#ffba22ce",
        "editor.wordHighlightTextBackground": "#6e92c141",
        "editor.wordHighlightTextBorder": "#c0766d41",
        "editorBracketHighlight.foreground1": "#9371c441",
        "editorBracketHighlight.foreground2": "#7498c741",
        "editorBracketHighlight.foreground3": "#906ec141",
        "editorBracketHighlight.foreground4": "#c774b041",
        "editorBracketHighlight.foreground5": "#69696941",
        "editorBracketHighlight.foreground6": "#65656541",
        "editorBracketHighlight.unexpectedBracket.foreground": "#65656541",
        "editorBracketMatch.background": "#7fc37041",
        "editorBracketMatch.border": "#c1776e41",
        "editorBracketPairGuide.activeBackground1": "#c673af41",
        "editorBracketPairGuide.activeBackground2": "#c0766d41",
        "editorBracketPairGuide.activeBackground3": "#65656541",
        "editorBracketPairGuide.activeBackground4": "#9775c841",
        "editorBracketPairGuide.activeBackground5": "#c572ae41",
        "editorBracketPairGuide.activeBackground6": "#74c7ab41",
        "editorBracketPairGuide.background1": "#111111fe",
        "editorBracketPairGuide.background2": "#111111fe",
        "editorBracketPairGuide.background3": "#111111fe",
        "editorBracketPairGuide.background4": "#111111fe",
        "editorBracketPairGuide.background5": "#111111fe",
        "editorBracketPairGuide.background6": "#111111fe",
        "editorCodeLens.foreground": "#e9e9e939",
        "editorCommentsWidget.rangeActiveBackground": "#111111fe",
        "editorCommentsWidget.rangeBackground": "#111111fe",
        "editorCommentsWidget.resolvedBorder": "#000000fe",
        "editorCommentsWidget.unresolvedBorder": "#ff6a6acb",
        "editorCursor.background": "#111111fe",
        "editorCursor.foreground": "#8d8d8dbe",
        "editorError.background": "#01010100",
        "editorError.border": "#01010100",
        "editorError.foreground": "#cc00ffce",
        "editorGhostText.background": "#111111fe",
        "editorGhostText.border": "#01010100",
        "editorGhostText.foreground": "#e1e1e133",
        "editorGroup.border": "#000000fe",
        "editorGroup.dropBackground": "#111111fe",
        "editorGroup.dropIntoPromptBackground": "#111111fe",
        "editorGroup.dropIntoPromptBorder": "#000000fe",
        "editorGroup.dropIntoPromptForeground": "#cdcdcdbe",
        "editorGroup.emptyBackground": "#111111fe",
        "editorGroup.focusedEmptyBorder": "#000000fe",
        "editorGroupHeader.border": "#000000fe",
        "editorGroupHeader.noTabsBackground": "#111111fe",
        "editorGroupHeader.tabsBackground": "#1d1d1da1",
        "editorGroupHeader.tabsBorder": "#01010100",
        "editorGutter.addedBackground": "#00cc00cb",
        "editorGutter.background": "#111111fe",
        "editorGutter.commentGlyphForeground": "#d9d9d9be",
        "editorGutter.commentRangeForeground": "#d9d9d9be",
        "editorGutter.commentUnresolvedGlyphForeground": "#00cc00cb",
        "editorGutter.deletedBackground": "#ff6a6acb",
        "editorGutter.foldingControlForeground": "#906ec141",
        "editorGutter.modifiedBackground": "#ffba22ce",
        "editorHint.border": "#01010100",
        "editorHint.foreground": "#6767ffa9",
        "editorHoverWidget.background": "#090909fe",
        "editorHoverWidget.border": "#000000fe",
        "editorHoverWidget.foreground": "#587cabfe",
        "editorHoverWidget.highlightForeground": "#d481bdca",
        "editorHoverWidget.statusBarBackground": "#111111fe",
        "editorIndentGuide.activeBackground1": "#9d9d9dbe",
        "editorIndentGuide.activeBackground2": "#9d9d9dbe",
        "editorIndentGuide.activeBackground3": "#a1a1a1be",
        "editorIndentGuide.activeBackground4": "#a5a5a5be",
        "editorIndentGuide.activeBackground5": "#a1a1a1be",
        "editorIndentGuide.activeBackground6": "#a1a1a1be",
        "editorIndentGuide.background1": "#89898941",
        "editorIndentGuide.background2": "#85858541",
        "editorIndentGuide.background3": "#c774b041",
        "editorIndentGuide.background4": "#71717141",
        "editorIndentGuide.background5": "#c1776e41",
        "editorIndentGuide.background6": "#6d6d6d41",
        "editorInfo.background": "#01010100",
        "editorInfo.border": "#01010100",
        "editorInfo.foreground": "#6767ffb8",
        "editorInlayHint.background": "#111111fe",
        "editorInlayHint.foreground": "#b5b5b5be",
        "editorInlayHint.parameterBackground": "#111111fe",
        "editorInlayHint.parameterForeground": "#c5c5c5be",
        "editorInlayHint.typeBackground": "#111111fe",
        "editorInlayHint.typeForeground": "#c9c9c9be",
        "editorLightBulb.foreground": "#ffba22ce",
        "editorLightBulbAutoFix.foreground": "#00cc00cb",
        "editorLineNumber.activeForeground": "#8d8d8dbe",
        "editorLineNumber.dimmedForeground": "#dddddd35",
        "editorLineNumber.foreground": "#dddddd3b",
        "editorLink.activeForeground": "#999999be",
        "editorMarkerNavigation.background": "#111111fe",
        "editorMarkerNavigationError.background": "#6700679f",
        "editorMarkerNavigationError.headerBackground": "#670067a6",
        "editorMarkerNavigationInfo.background": "#6767ffc1",
        "editorMarkerNavigationInfo.headerBackground": "#6767ffad",
        "editorMarkerNavigationWarning.background": "#7a7a00fe",
        "editorMarkerNavigationWarning.headerBackground": "#7a7a00fe",
        "editorOverviewRuler.addedForeground": "#00cc00cb",
        "editorOverviewRuler.background": "#0d0d0dfe",
        "editorOverviewRuler.border": "#0d0d0dfe",
        "editorOverviewRuler.bracketMatchForeground": "#0d0d0dfe",
        "editorOverviewRuler.commentForeground": "#0d0d0dfe",
        "editorOverviewRuler.commentUnresolvedForeground": "#0d0d0dfe",
        "editorOverviewRuler.commonContentForeground": "#0d0d0dfe",
        "editorOverviewRuler.currentContentForeground": "#cecececa",
        "editorOverviewRuler.deletedForeground": "#ff6a6acb",
        "editorOverviewRuler.errorForeground": "#cc00ffce",
        "editorOverviewRuler.findMatchForeground": "#00a5a5bb",
        "editorOverviewRuler.incomingContentForeground": "#00cc00cb",
        "editorOverviewRuler.infoForeground": "#6767ffc1",
        "editorOverviewRuler.modifiedForeground": "#ffba22ce",
        "editorOverviewRuler.rangeHighlightForeground": "#0d0d0dfe",
        "editorOverviewRuler.selectionHighlightForeground": "#6767ffb0",
        "editorOverviewRuler.warningForeground": "#0d0d0dfe",
        "editorOverviewRuler.wordHighlightForeground": "#0d0d0dfe",
        "editorOverviewRuler.wordHighlightStrongForeground": "#0d0d0dfe",
        "editorOverviewRuler.wordHighlightTextForeground": "#0d0d0dfe",
        "editorPane.background": "#111111fe",
        "editorRuler.foreground": "#c16eaa41",
        "editorStickyScroll.background": "#111111fe",
        "editorStickyScrollHover.background": "#111111fe",
        "editorSuggestWidget.background": "#090909fe",
        "editorSuggestWidget.border": "#01010100",
        "editorSuggestWidget.focusHighlightForeground": "#70c3a7fe",
        "editorSuggestWidget.foreground": "#90d481fe",
        "editorSuggestWidget.highlightForeground": "#d27fbbca",
        "editorSuggestWidget.selectedBackground": "#9270c341",
        "editorSuggestWidget.selectedForeground": "#b9b666ca",
        "editorSuggestWidget.selectedIconForeground": "#d17ebaca",
        "editorSuggestWidgetStatus.foreground": "#7599c8fe",
        "editorUnicodeHighlight.background": "#7fc37041",
        "editorUnicodeHighlight.border": "#6e92c141",
        "editorUnnecessaryCode.border": "#bc5a00fe",
        "editorUnnecessaryCode.opacity": "#bc5a00fe",
        "editorWarning.background": "#01010100",
        "editorWarning.border": "#01010100",
        "editorWarning.foreground": "#e6e600ce",
        "editorWhitespace.foreground": "#b9b9b9be",
        "editorWidget.background": "#111111fe",
        "editorWidget.border": "#000000fe",
        "editorWidget.foreground": "#cdcdcdbe",
        "editorWidget.resizeBorder": "#000000fe",
        "errorForeground": "#cc00ffce",
        "extensionBadge.remoteBackground": "#b1b1b1be",
        "extensionBadge.remoteForeground": "#0d0d0dfe",
        "extensionButton.background": "#252525ce",
        "extensionButton.foreground": "#bdbdbdbe",
        "extensionButton.hoverBackground": "#8989891e",
        "extensionButton.prominentBackground": "#111111fe",
        "extensionButton.prominentForeground": "#d5d5d5be",
        "extensionButton.prominentHoverBackground": "#111111fe",
        "extensionButton.separator": "#bdba6af5",
        "extensionIcon.preReleaseForeground": "#9270c3fe",
        "extensionIcon.sponsorForeground": "#81c572fe",
        "extensionIcon.starForeground": "#8bdec2fe",
        "extensionIcon.verifiedForeground": "#79bd6afe",
        "focusBorder": "#01010100",
        "foreground": "#d9d9d9be",
        "gitDecoration.addedResourceForeground": "#00cc00cb",
        "gitDecoration.deletedResourceForeground": "#ff6a6acb",
        "gitDecoration.modifiedResourceForeground": "#ffba22ce",
        "gitDecoration.renamedResourceForeground": "#84a3f9b1",
        "gitDecoration.stageDeletedResourceForeground": "#ff6a6acb",
        "gitDecoration.stageModifiedResourceForeground": "#00cc00cb",
        "gitDecoration.untrackedResourceForeground": "#00a5a5ca",
        "icon.foreground": "#999999be",
        "inlineChat.background": "#111111fe",
        "inlineChat.border": "#000000fe",
        "inlineChat.regionHighlight": "#71717141",
        "inlineChat.shadow": "#01010100",
        "inlineChatDiff.inserted": "#78cbaffc",
        "inlineChatDiff.removed": "#0d0d0df5",
        "inlineChatInput.background": "#0d0d0dfe",
        "inlineChatInput.border": "#9d9d9dbe",
        "inlineChatInput.focusBorder": "#01010100",
        "inlineChatInput.placeholderForeground": "#c5c5c544",
        "input.background": "#0d0d0dfe",
        "input.border": "#9d9d9dbe",
        "input.foreground": "#d5d5d5be",
        "input.placeholderForeground": "#c1c1c146",
        "inputOption.activeBackground": "#69696941",
        "inputOption.activeBorder": "#959595be",
        "inputOption.activeForeground": "#b9b9b9be",
        "inputOption.hoverBackground": "#0d0d0dfe",
        "inputValidation.errorBackground": "#670067c2",
        "inputValidation.errorBorder": "#adadadbe",
        "inputValidation.errorForeground": "#cc00ffce",
        "inputValidation.infoBackground": "#6767ffa5",
        "inputValidation.infoBorder": "#9d9d9dbe",
        "inputValidation.infoForeground": "#b5b5b5be",
        "inputValidation.warningBackground": "#7a7a00fe",
        "inputValidation.warningBorder": "#9d9d9dbe",
        "inputValidation.warningForeground": "#e6e600ce",
        "interactive.activeCodeBorder": "#8d8d8dbe",
        "interactive.inactiveCodeBorder": "#a9a9a9be",
        "keybindingLabel.background": "#111111fe",
        "keybindingLabel.border": "#000000fe",
        "keybindingLabel.bottomBorder": "#000000fe",
        "keybindingLabel.foreground": "#d9d9d9be",
        "keybindingTable.headerBackground": "#111111fe",
        "keybindingTable.rowsBackground": "#111111fe",
        "list.activeSelectionBackground": "#65656541",
        "list.activeSelectionForeground": "#5579a8ca",
        "list.activeSelectionIconForeground": "#b15e9aca",
        "list.deemphasizedForeground": "#d9d9d9be",
        "list.dropBackground": "#111111fe",
        "list.errorForeground": "#cc00ffce",
        "list.filterMatchBackground": "#111111fe",
        "list.filterMatchBorder": "#000000fe",
        "list.focusAndSelectionOutline": "#85858541",
        "list.focusBackground": "#7296c541",
        "list.focusForeground": "#d1d1d1be",
        "list.focusHighlightForeground": "#d58b82fe",
        "list.focusOutline": "#6c90bf41",
        "list.highlightForeground": "#7498c7ca",
        "list.hoverBackground": "#7979791e",
        "list.hoverForeground": "#8de0c4fe",
        "list.inactiveFocusBackground": "#01010129",
        "list.inactiveFocusOutline": "#75757541",
        "list.inactiveSelectionBackground": "#0d0d0dfe",
        "list.inactiveSelectionForeground": "#7ccfb3ca",
        "list.inactiveSelectionIconForeground": "#a9a656ca",
        "list.invalidItemForeground": "#bdbdbdbe",
        "list.warningForeground": "#e6e600ce",
        "listFilterWidget.background": "#111111fe",
        "listFilterWidget.noMatchesOutline": "#71c4a841",
        "listFilterWidget.outline": "#65656541",
        "listFilterWidget.shadow": "#01010100",
        "menu.background": "#0d0d0dfe",
        "menu.border": "#01010100",
        "menu.foreground": "#e5e5e5be",
        "menu.selectionBackground": "#8181811e",
        "menu.selectionBorder": "#01010100",
        "menu.selectionForeground": "#789ccbca",
        "menu.separatorBackground": "#e9e9e9be",
        "menubar.selectionBackground": "#8989891e",
        "menubar.selectionBorder": "#01010100",
        "menubar.selectionForeground": "#c875b1ca",
        "merge.border": "#000000fe",
        "merge.commonContentBackground": "#111111fe",
        "merge.commonHeaderBackground": "#111111fe",
        "merge.currentContentBackground": "#9aff9a21",
        "merge.currentHeaderBackground": "#004000cb",
        "merge.incomingContentBackground": "#00cc00cb",
        "merge.incomingHeaderBackground": "#004000cb",
        "mergeEditor.change.background": "#111111fe",
        "mergeEditor.change.word.background": "#111111fe",
        "mergeEditor.changeBase.background": "#111111fe",
        "mergeEditor.changeBase.word.background": "#111111fe",
        "mergeEditor.conflict.handled.minimapOverViewRuler": "#656565f4",
        "mergeEditor.conflict.handledFocused.border": "#000000fe",
        "mergeEditor.conflict.handledUnfocused.border": "#01010123",
        "mergeEditor.conflict.input1.background": "#0d0d0dfe",
        "mergeEditor.conflict.input2.background": "#0d0d0dfe",
        "mergeEditor.conflict.unhandled.minimapOverViewRuler": "#91d582f1",
        "mergeEditor.conflict.unhandledFocused.border": "#000000fe",
        "mergeEditor.conflict.unhandledUnfocused.border": "#09090927",
        "mergeEditor.conflictingLines.background": "#111111fe",
        "minimap.background": "#111111fe",
        "minimap.errorHighlight": "#cc00ffce",
        "minimap.findMatchHighlight": "#00a5a5c3",
        "minimap.foregroundOpacity": "#d1d1d1be",
        "minimap.selectionHighlight": "#6767ffa7",
        "minimap.selectionOccurrenceHighlight": "#84a3f9c6",
        "minimap.warningHighlight": "#e6e600ce",
        "minimapGutter.addedBackground": "#00cc00cb",
        "minimapGutter.deletedBackground": "#400000cb",
        "minimapGutter.modifiedBackground": "#ffba22ce",
        "minimapSlider.activeBackground": "#6d6d6d41",
        "minimapSlider.background": "#adadadbe",
        "minimapSlider.hoverBackground": "#83c77441",
        "notebook.cellBorderColor": "#000000fe",
        "notebook.cellEditorBackground": "#111111fe",
        "notebook.cellHoverBackground": "#111111fe",
        "notebook.cellInsertionIndicator": "#b5b5b5f6",
        "notebook.cellStatusBarItemHoverBackground": "#111111fe",
        "notebook.cellToolbarSeparator": "#cd7ab6f3",
        "notebook.editorBackground": "#111111fe",
        "notebook.focusedCellBackground": "#0d0d0dfe",
        "notebook.focusedCellBorder": "#959595be",
        "notebook.focusedEditorBorder": "#000000fe",
        "notebook.inactiveFocusedCellBorder": "#9d9d9dbe",
        "notebook.inactiveSelectedCellBorder": "#b1b1b1be",
        "notebook.outputContainerBackgroundColor": "#111111fe",
        "notebook.outputContainerBorderColor": "#000000fe",
        "notebook.selectedCellBackground": "#6c90bf41",
        "notebook.selectedCellBorder": "#000000fe",
        "notebook.symbolHighlightBackground": "#85858541",
        "notebookEditorOverviewRuler.runningCellForeground": "#0d0d0dfe",
        "notebookScrollbarSlider.activeBackground": "#bf6ca841",
        "notebookScrollbarSlider.background": "#adadadbe",
        "notebookScrollbarSlider.hoverBackground": "#75c8ac41",
        "notebookStatusErrorIcon.foreground": "#a9a9a9be",
        "notebookStatusRunningIcon.foreground": "#919191be",
        "notebookStatusSuccessIcon.foreground": "#9d9d9dbe",
        "notificationCenter.border": "#000000fe",
        "notificationCenterHeader.background": "#111111fe",
        "notificationCenterHeader.foreground": "#b9b9b9be",
        "notificationLink.foreground": "#c5c5c5be",
        "notificationToast.border": "#000000fe",
        "notifications.background": "#111111fe",
        "notifications.border": "#000000fe",
        "notifications.foreground": "#d5d5d5be",
        "notificationsErrorIcon.foreground": "#b1b1b1be",
        "notificationsInfoIcon.foreground": "#8d8d8dbe",
        "notificationsWarningIcon.foreground": "#adadadbe",
        "panel.background": "#111111fe",
        "panel.border": "#000000fe",
        "panel.dropBorder": "#000000fe",
        "panelInput.border": "#a9a9a9be",
        "panelSection.border": "#000000fe",
        "panelSection.dropBackground": "#111111fe",
        "panelSectionHeader.background": "#111111fe",
        "panelSectionHeader.border": "#000000fe",
        "panelSectionHeader.foreground": "#d9d9d9be",
        "panelTitle.activeBorder": "#919191be",
        "panelTitle.activeForeground": "#a1a1a1be",
        "panelTitle.inactiveForeground": "#c1c1c145",
        "peekView.border": "#000000fe",
        "peekViewEditor.background": "#111111fe",
        "peekViewEditor.matchHighlightBackground": "#9775c841",
        "peekViewEditor.matchHighlightBorder": "#9775c841",
        "peekViewEditorGutter.background": "#111111fe",
        "peekViewEditorStickyScroll.background": "#111111fe",
        "peekViewResult.background": "#111111fe",
        "peekViewResult.fileForeground": "#cdcdcdbe",
        "peekViewResult.lineForeground": "#d9d9d9be",
        "peekViewResult.matchHighlightBackground": "#7bbf6c41",
        "peekViewResult.selectionBackground": "#7d7d7d41",
        "peekViewResult.selectionForeground": "#906ec1ca",
        "peekViewTitle.background": "#111111fe",
        "peekViewTitleDescription.foreground": "#cdcdcdbe",
        "peekViewTitleLabel.foreground": "#c5c5c5be",
        "pickerGroup.border": "#000000fe",
        "pickerGroup.foreground": "#b5b5b5be",
        "ports.iconRunningProcessForeground": "#71b562fe",
        "problemsErrorIcon.foreground": "#cc00ffce",
        "problemsInfoIcon.foreground": "#6767ffca",
        "problemsWarningIcon.foreground": "#e6e600ce",
        "profileBadge.background": "#9d9d9dbe",
        "profileBadge.foreground": "#0d0d0dfe",
        "progressBar.background": "#111111fe",
        "quickInput.background": "#0d0d0dfe",
        "quickInput.foreground": "#959595be",
        "quickInputList.focusBackground": "#75c8ac41",
        "quickInputList.focusForeground": "#b9b9b9be",
        "quickInputList.focusIconForeground": "#6eb25ffe",
        "quickInputTitle.background": "#0d0d0dfe",
        "sash.hoverBorder": "#000000fe",
        "scrollbar.shadow": "#01010100",
        "scrollbarSlider.activeBackground": "#85858541",
        "scrollbarSlider.background": "#9d9d9dbe",
        "scrollbarSlider.hoverBackground": "#c4c17141",
        "search.resultsInfoForeground": "#bdbdbdbe",
        "searchEditor.findMatchBackground": "#c67c7341",
        "searchEditor.findMatchBorder": "#c1776e41",
        "searchEditor.textInputBorder": "#9d9d9dbe",
        "selection.background": "#111111fe",
        "settings.checkboxBackground": "#111111fe",
        "settings.checkboxBorder": "#a9a9a9be",
        "settings.checkboxForeground": "#d9d9d9be",
        "settings.dropdownBackground": "#111111fe",
        "settings.dropdownBorder": "#959595be",
        "settings.dropdownForeground": "#c5c5c5be",
        "settings.dropdownListBorder": "#a9a9a9be",
        "settings.focusedRowBackground": "#9371c441",
        "settings.focusedRowBorder": "#000000fe",
        "settings.headerBorder": "#000000fe",
        "settings.headerForeground": "#c1c1c1be",
        "settings.modifiedItemIndicator": "#ffba22ce",
        "settings.numberInputBackground": "#0d0d0dfe",
        "settings.numberInputBorder": "#919191be",
        "settings.numberInputForeground": "#d9d9d9be",
        "settings.rowHoverBackground": "#111111fe",
        "settings.sashBorder": "#000000fe",
        "settings.settingsHeaderHoverForeground": "#b76d64fe",
        "settings.textInputBackground": "#0d0d0dfe",
        "settings.textInputBorder": "#a5a5a5be",
        "settings.textInputForeground": "#c9c9c9be",
        "sideBar.background": "#111111fe",
        "sideBar.border": "#000000fe",
        "sideBar.dropBackground": "#111111fe",
        "sideBar.foreground": "#d1d1d1be",
        "sideBarSectionHeader.background": "#01010100",
        "sideBarSectionHeader.border": "#000000fe",
        "sideBarSectionHeader.foreground": "#b9b9b9be",
        "sideBarTitle.foreground": "#c9c9c9be",
        "sideBySideEditor.horizontalBorder": "#000000fe",
        "sideBySideEditor.verticalBorder": "#000000fe",
        "simpleFindWidget.sashBorder": "#000000fe",
        "statusBar.background": "#111111fe",
        "statusBar.border": "#000000fe",
        "statusBar.debuggingBackground": "#670067c6",
        "statusBar.debuggingBorder": "#000000fe",
        "statusBar.debuggingForeground": "#c5c5c5be",
        "statusBar.focusBorder": "#01010100",
        "statusBar.foreground": "#cdcdcdbe",
        "statusBar.noFolderBackground": "#111111fe",
        "statusBar.noFolderBorder": "#000000fe",
        "statusBar.noFolderForeground": "#d9d9d9be",
        "statusBarItem.activeBackground": "#c87e7541",
        "statusBarItem.compactHoverBackground": "#111111fe",
        "statusBarItem.errorBackground": "#400000cb",
        "statusBarItem.errorForeground": "#ff6a6acb",
        "statusBarItem.errorHoverBackground": "#670067c1",
        "statusBarItem.errorHoverForeground": "#cc00ffce",
        "statusBarItem.focusBorder": "#01010100",
        "statusBarItem.hoverBackground": "#111111fe",
        "statusBarItem.hoverForeground": "#9f7dd0fe",
        "statusBarItem.offlineBackground": "#111111fe",
        "statusBarItem.offlineForeground": "#bdbdbdbe",
        "statusBarItem.offlineHoverBackground": "#111111fe",
        "statusBarItem.offlineHoverForeground": "#78bc69fe",
        "statusBarItem.prominentBackground": "#111111fe",
        "statusBarItem.prominentForeground": "#b5b5b5be",
        "statusBarItem.prominentHoverBackground": "#111111fe",
        "statusBarItem.prominentHoverForeground": "#9371c4fe",
        "statusBarItem.remoteBackground": "#111111fe",
        "statusBarItem.remoteForeground": "#d5d5d5be",
        "statusBarItem.remoteHoverBackground": "#111111fe",
        "statusBarItem.remoteHoverForeground": "#8664b7fe",
        "statusBarItem.warningBackground": "#7a7a00fe",
        "statusBarItem.warningForeground": "#e6e600ce",
        "statusBarItem.warningHoverBackground": "#7a7a00fe",
        "statusBarItem.warningHoverForeground": "#e6e600ce",
        "symbolIcon.arrayForeground": "#70b461fe",
        "symbolIcon.booleanForeground": "#b56b62fe",
        "symbolIcon.classForeground": "#d27fbbfe",
        "symbolIcon.colorForeground": "#ab6158fe",
        "symbolIcon.constantForeground": "#8cdfc3fe",
        "symbolIcon.constructorForeground": "#7abe6bfe",
        "symbolIcon.enumeratorForeground": "#63b69afe",
        "symbolIcon.enumeratorMemberForeground": "#c2786ffe",
        "symbolIcon.eventForeground": "#80c471fe",
        "symbolIcon.fieldForeground": "#d2cf7ffe",
        "symbolIcon.fileForeground": "#88dbbffe",
        "symbolIcon.folderForeground": "#65656541",
        "symbolIcon.functionForeground": "#a75490fe",
        "symbolIcon.interfaceForeground": "#a8a555fe",
        "symbolIcon.keyForeground": "#bb68a4fe",
        "symbolIcon.keywordForeground": "#de8bc7fe",
        "symbolIcon.methodForeground": "#85c976fe",
        "symbolIcon.moduleForeground": "#7553a6fe",
        "symbolIcon.namespaceForeground": "#62b599fe",
        "symbolIcon.nullForeground": "#c5c272fe",
        "symbolIcon.numberForeground": "#6a8ebdfe",
        "symbolIcon.objectForeground": "#e0968dfe",
        "symbolIcon.operatorForeground": "#96da87fe",
        "symbolIcon.packageForeground": "#789ccbfe",
        "symbolIcon.propertyForeground": "#d7d484fe",
        "symbolIcon.referenceForeground": "#dfdc8cfe",
        "symbolIcon.snippetForeground": "#577baafe",
        "symbolIcon.stringForeground": "#c8c575fe",
        "symbolIcon.structForeground": "#e0dd8dfe",
        "symbolIcon.textForeground": "#789ccbfe",
        "symbolIcon.typeParameterForeground": "#7856a9fe",
        "symbolIcon.unitForeground": "#6dc0a4fe",
        "symbolIcon.variableForeground": "#81a5d4fe",
        "tab.activeBackground": "#111111fe",
        "tab.activeBorder": "#01010100",
        "tab.activeBorderTop": "#adadadbe",
        "tab.activeForeground": "#a5a5a5be",
        "tab.activeModifiedBorder": "#a9a9a9be",
        "tab.border": "#01010100",
        "tab.hoverBackground": "#111111fe",
        "tab.hoverBorder": "#000000fe",
        "tab.hoverForeground": "#ab89dcfe",
        "tab.inactiveBackground": "#212121a1",
        "tab.inactiveForeground": "#adadad47",
        "tab.inactiveModifiedBorder": "#8d8d8dbe",
        "tab.lastPinnedBorder": "#000000fe",
        "tab.unfocusedActiveBackground": "#1111112b",
        "tab.unfocusedActiveBorder": "#01010100",
        "tab.unfocusedActiveBorderTop": "#85858541",
        "tab.unfocusedActiveForeground": "#c5c5c542",
        "tab.unfocusedActiveModifiedBorder": "#919191be",
        "tab.unfocusedHoverBackground": "#05050526",
        "tab.unfocusedHoverBorder": "#09090923",
        "tab.unfocusedHoverForeground": "#d6d383fe",
        "tab.unfocusedInactiveBackground": "#0505052a",
        "tab.unfocusedInactiveForeground": "#b1b1b146",
        "tab.unfocusedInactiveModifiedBorder": "#959595be",
        "terminal.ansiBlack": "#0c0c0cfe",
        "terminal.ansiBlue": "#6767ffaa",
        "terminal.ansiBrightBlack": "#333333c5",
        "terminal.ansiBrightBlue": "#84a3f9b3",
        "terminal.ansiBrightCyan": "#00a5a5ad",
        "terminal.ansiBrightGreen": "#00cc00cb",
        "terminal.ansiBrightMagenta": "#cc00ffce",
        "terminal.ansiBrightRed": "#ff6a6acb",
        "terminal.ansiBrightWhite": "#f4f4f4be",
        "terminal.ansiBrightYellow": "#e6e600ce",
        "terminal.ansiCyan": "#008b8b9c",
        "terminal.ansiGreen": "#004000cb",
        "terminal.ansiMagenta": "#6700679b",
        "terminal.ansiRed": "#400000cb",
        "terminal.ansiWhite": "#cecece9a",
        "terminal.ansiYellow": "#7a7a00fe",
        "terminal.background": "#111111fe",
        "terminal.border": "#000000fe",
        "terminal.dropBackground": "#111111fe",
        "terminal.findMatchBackground": "#111111fe",
        "terminal.findMatchBorder": "#000000fe",
        "terminal.findMatchHighlightBackground": "#85858541",
        "terminal.findMatchHighlightBorder": "#c4c17141",
        "terminal.foreground": "#e1e1e1be",
        "terminal.hoverHighlightBackground": "#c87e7541",
        "terminal.inactiveSelectionBackground": "#0909092e",
        "terminal.selectionBackground": "#7bbf6c41",
        "terminal.selectionForeground": "#aeab5bca",
        "terminal.tab.activeBorder": "#01010100",
        "terminalCommandDecoration.defaultBackground": "#b2af5fee",
        "terminalCommandDecoration.errorBackground": "#ff6a6acb",
        "terminalCommandDecoration.successBackground": "#00cc00cb",
        "terminalCursor.background": "#111111fe",
        "terminalCursor.foreground": "#8d8d8dbe",
        "terminalOverviewRuler.cursorForeground": "#c26fab41",
        "terminalOverviewRuler.findMatchForeground": "#80c47141",
        "testing.iconErrored": "#cc00ffce",
        "testing.iconFailed": "#ff6a6acb",
        "testing.iconPassed": "#00cc00cb",
        "testing.iconQueued": "#84a3f9c9",
        "testing.iconSkipped": "#c0c0c0c8",
        "testing.iconUnset": "#808080ca",
        "testing.message.error.decorationForeground": "#959595be",
        "testing.message.error.lineBackground": "#670067b5",
        "testing.message.info.decorationForeground": "#919191be",
        "testing.message.info.lineBackground": "#6767ffaa",
        "testing.peekBorder": "#000000fe",
        "testing.peekHeaderBackground": "#111111fe",
        "testing.runAction": "#00cc00cb",
        "textBlockQuote.background": "#111111fe",
        "textBlockQuote.border": "#000000fe",
        "textCodeBlock.background": "#111111fe",
        "textLink.activeForeground": "#999999be",
        "textLink.foreground": "#6767ffa0",
        "textPreformat.foreground": "#b5b5b5be",
        "textSeparator.foreground": "#c1c1c1be",
        "titleBar.activeBackground": "#0d0d0dfe",
        "titleBar.activeForeground": "#ddddddbe",
        "titleBar.border": "#01010100",
        "titleBar.inactiveBackground": "#09090928",
        "titleBar.inactiveForeground": "#b1b1b147",
        "toolbar.activeBackground": "#75757541",
        "toolbar.hoverBackground": "#111111fe",
        "toolbar.hoverOutline": "#85858541",
        "tree.inactiveIndentGuidesStroke": "#c370ac41",
        "tree.indentGuidesStroke": "#adadadbe",
        "tree.tableColumnsBorder": "#000000fe",
        "tree.tableOddRowsBackground": "#111111fe",
        "walkThrough.embeddedEditorBackground": "#111111fe",
        "walkthrough.stepTitle.foreground": "#d1d1d1be",
        "welcomePage.background": "#111111fe",
        "welcomePage.progress.background": "#111111fe",
        "welcomePage.progress.foreground": "#d1d1d1be",
        "welcomePage.tileBackground": "#111111fe",
        "welcomePage.tileBorder": "#000000fe",
        "welcomePage.tileHoverBackground": "#111111fe",
        "widget.border": "#000000fe",
        "widget.shadow": "#01010100",
        "window.activeBorder": "#adadadbe",
        "window.inactiveBorder": "#a9a9a9be"
    },
    "tokenColors": [
        {
            "scope": "comment.block.documentation.c",
            "settings": {
                "foreground": "#e1e1e14e"
            }
        },
        {
            "scope": "comment.block.html",
            "settings": {
                "foreground": "#dddddd4e"
            }
        },
        {
            "scope": "comment.block.javadoc.java",
            "settings": {
                "foreground": "#dddddd4e"
            }
        },
        {
            "scope": "comment.block.powershell",
            "settings": {
                "foreground": "#e5e5e54e"
            }
        },
        {
            "scope": "comment.block.xml",
            "settings": {
                "foreground": "#e1e1e14e"
            }
        },
        {
            "scope": "comment.line.double-slash.c",
            "settings": {
                "foreground": "#e9e9e94e"
            }
        },
        {
            "scope": "comment.line.double-slash.cpp",
            "settings": {
                "foreground": "#e9e9e94e"
            }
        },
        {
            "scope": "comment.line.double-slash.java",
            "settings": {
                "foreground": "#e5e5e54e"
            }
        },
        {
            "scope": "comment.line.double-slash.js",
            "settings": {
                "foreground": "#e5e5e54e"
            }
        },
        {
            "scope": "comment.line.number-sign.makefile",
            "settings": {
                "foreground": "#e9e9e94e"
            }
        },
        {
            "scope": "comment.line.number-sign.python",
            "settings": {
                "foreground": "#e5e5e54e"
            }
        },
        {
            "scope": "comment.line.number-sign.yaml",
            "settings": {
                "foreground": "#e9e9e94e"
            }
        },
        {
            "scope": "comment.line.percentage.erlang",
            "settings": {
                "foreground": "#e9e9e94e"
            }
        },
        {
            "scope": "comment.line.powershell",
            "settings": {
                "foreground": "#e5e5e54e"
            }
        },
        {
            "scope": "comment.source.cmake",
            "settings": {
                "foreground": "#e5e5e54e"
            }
        },
        {
            "scope": "comment.source.cmakecache",
            "settings": {
                "foreground": "#dddddd4e"
            }
        },
        {
            "scope": "constant.character",
            "settings": {
                "foreground": "#c9c676ee"
            }
        },
        {
            "scope": "constant.character.character-class.regexp",
            "settings": {
                "foreground": "#ae645bee"
            }
        },
        {
            "scope": "constant.character.escape",
            "settings": {
                "foreground": "#8ace7bee"
            }
        },
        {
            "scope": "constant.character.set.regexp",
            "settings": {
                "foreground": "#9f7dd0ee"
            }
        },
        {
            "scope": "constant.language",
            "settings": {
                "foreground": "#c37970ee"
            }
        },
        {
            "scope": "constant.numeric",
            "settings": {
                "foreground": "#b36960ee"
            }
        },
        {
            "scope": "constant.numeric.dec.python",
            "settings": {
                "foreground": "#aaa757ee"
            }
        },
        {
            "scope": "constant.other.caps.python",
            "settings": {
                "foreground": "#80c471ee"
            }
        },
        {
            "scope": "constant.other.character-class.regexp",
            "settings": {
                "foreground": "#8c6abdee"
            }
        },
        {
            "scope": "constant.other.character-class.set.regexp",
            "settings": {
                "foreground": "#b8b565ee"
            }
        },
        {
            "scope": "constant.other.color.rgb-value",
            "settings": {
                "foreground": "#7599c8ee"
            }
        },
        {
            "scope": "constant.other.placeholder",
            "settings": {
                "foreground": "#ae645bee"
            }
        },
        {
            "scope": "constant.other.rgb-value",
            "settings": {
                "foreground": "#7fd2b6ee"
            }
        },
        {
            "scope": "constant.regexp",
            "settings": {
                "foreground": "#ce847bee"
            }
        },
        {
            "scope": "constant.sha.git-rebase",
            "settings": {
                "foreground": "#d27fbbee"
            }
        },
        {
            "scope": "emphasis",
            "settings": {
                "foreground": "#bb68a4ee"
            }
        },
        {
            "scope": "entity.name.class",
            "settings": {
                "foreground": "#5579a8ee"
            }
        },
        {
            "scope": "entity.name.function",
            "settings": {
                "foreground": "#8664b7ee"
            }
        },
        {
            "scope": "entity.name.function.preprocessor",
            "settings": {
                "foreground": "#9270c3ee"
            }
        },
        {
            "scope": "entity.name.function.python",
            "settings": {
                "foreground": "#668ab9ee"
            }
        },
        {
            "scope": "entity.name.label",
            "settings": {
                "foreground": "#7fc370ee"
            }
        },
        {
            "scope": "entity.name.namespace",
            "settings": {
                "foreground": "#c976b2ee"
            }
        },
        {
            "scope": "entity.name.operator",
            "settings": {
                "foreground": "#6cbfa3ee"
            }
        },
        {
            "scope": "entity.name.operator.custom-literal",
            "settings": {
                "foreground": "#80c471ee"
            }
        },
        {
            "scope": "entity.name.scope-resolution",
            "settings": {
                "foreground": "#a7a454ee"
            }
        },
        {
            "scope": "entity.name.tag",
            "settings": {
                "foreground": "#7856a9ee"
            }
        },
        {
            "scope": "entity.name.tag.css",
            "settings": {
                "foreground": "#cfcc7cee"
            }
        },
        {
            "scope": "entity.name.type",
            "settings": {
                "foreground": "#b1ae5eee"
            }
        },
        {
            "scope": "entity.name.variable",
            "settings": {
                "foreground": "#74b865ee"
            }
        },
        {
            "scope": "entity.other.attribute",
            "settings": {
                "foreground": "#6baf5cee"
            }
        },
        {
            "scope": "entity.other.attribute-name",
            "settings": {
                "foreground": "#b865a1ee"
            }
        },
        {
            "scope": "entity.other.attribute-name.class.css",
            "settings": {
                "foreground": "#6589b8ee"
            }
        },
        {
            "scope": "entity.other.attribute-name.class.mixin.css",
            "settings": {
                "foreground": "#6488b7ee"
            }
        },
        {
            "scope": "entity.other.attribute-name.id",
            "settings": {
                "foreground": "#c4c171ee"
            }
        },
        {
            "scope": "entity.other.attribute-name.id.css",
            "settings": {
                "foreground": "#61b498ee"
            }
        },
        {
            "scope": "entity.other.attribute-name.parent-selector.css",
            "settings": {
                "foreground": "#b9b666ee"
            }
        },
        {
            "scope": "entity.other.attribute-name.pseudo-class.css",
            "settings": {
                "foreground": "#b966a2ee"
            }
        },
        {
            "scope": "entity.other.attribute-name.pseudo-element.css",
            "settings": {
                "foreground": "#74b865ee"
            }
        },
        {
            "scope": "entity.other.attribute-name.scss",
            "settings": {
                "foreground": "#c77d74ee"
            }
        },
        {
            "scope": "entity.other.document.begin.yaml",
            "settings": {
                "foreground": "#e9e9e94e"
            }
        },
        {
            "scope": "entity.other.inherited-class",
            "settings": {
                "foreground": "#c97f76ee"
            }
        },
        {
            "scope": "header",
            "settings": {
                "foreground": "#6cbfa3ee"
            }
        },
        {
            "scope": "invalid",
            "settings": {
                "foreground": "#69bca0ee"
            }
        },
        {
            "scope": "keyword",
            "settings": {
                "foreground": "#bb68a4ee"
            }
        },
        {
            "scope": "keyword.control",
            "settings": {
                "foreground": "#7195c4ee"
            }
        },
        {
            "scope": "keyword.control.anchor.regexp",
            "settings": {
                "foreground": "#ab6158ee"
            }
        },
        {
            "scope": "keyword.control.import.python",
            "settings": {
                "foreground": "#b5b262ee"
            }
        },
        {
            "scope": "keyword.operator",
            "settings": {
                "foreground": "#cb8178ee"
            }
        },
        {
            "scope": "keyword.operator.alignas",
            "settings": {
                "foreground": "#c2786fee"
            }
        },
        {
            "scope": "keyword.operator.alignof",
            "settings": {
                "foreground": "#cb8178ee"
            }
        },
        {
            "scope": "keyword.operator.cast",
            "settings": {
                "foreground": "#8b69bcee"
            }
        },
        {
            "scope": "keyword.operator.delete",
            "settings": {
                "foreground": "#9876c9ee"
            }
        },
        {
            "scope": "keyword.operator.documentation.powershell",
            "settings": {
                "foreground": "#e1e1e14e"
            }
        },
        {
            "scope": "keyword.operator.expression",
            "settings": {
                "foreground": "#aca959ee"
            }
        },
        {
            "scope": "keyword.operator.instanceof",
            "settings": {
                "foreground": "#66aa57ee"
            }
        },
        {
            "scope": "keyword.operator.logical.python",
            "settings": {
                "foreground": "#7c5aadee"
            }
        },
        {
            "scope": "keyword.operator.minus.exponent",
            "settings": {
                "foreground": "#6fb360ee"
            }
        },
        {
            "scope": "keyword.operator.negation.regexp",
            "settings": {
                "foreground": "#9270c3ee"
            }
        },
        {
            "scope": "keyword.operator.new",
            "settings": {
                "foreground": "#c0bd6dee"
            }
        },
        {
            "scope": "keyword.operator.noexcept",
            "settings": {
                "foreground": "#cfcc7cee"
            }
        },
        {
            "scope": "keyword.operator.or.regexp",
            "settings": {
                "foreground": "#af655cee"
            }
        },
        {
            "scope": "keyword.operator.plus.exponent",
            "settings": {
                "foreground": "#6aae5bee"
            }
        },
        {
            "scope": "keyword.operator.quantifier.regexp",
            "settings": {
                "foreground": "#c8c575ee"
            }
        },
        {
            "scope": "keyword.operator.sizeof",
            "settings": {
                "foreground": "#ccc979ee"
            }
        },
        {
            "scope": "keyword.operator.typeid",
            "settings": {
                "foreground": "#bdba6aee"
            }
        },
        {
            "scope": "keyword.operator.wordlike",
            "settings": {
                "foreground": "#68ac59ee"
            }
        },
        {
            "scope": "keyword.other.operator",
            "settings": {
                "foreground": "#61b498ee"
            }
        },
        {
            "scope": "keyword.other.package.java",
            "settings": {
                "foreground": "#74c7abee"
            }
        },
        {
            "scope": "keyword.other.unit",
            "settings": {
                "foreground": "#c16eaaee"
            }
        },
        {
            "scope": "keyword.other.using",
            "settings": {
                "foreground": "#bb68a4ee"
            }
        },
        {
            "scope": "markup.bold",
            "settings": {
                "foreground": "#c5c272ee"
            }
        },
        {
            "scope": "markup.changed",
            "settings": {
                "foreground": "#c673afee"
            }
        },
        {
            "scope": "markup.deleted",
            "settings": {
                "foreground": "#6cbfa3ee"
            }
        },
        {
            "scope": "markup.fenced_code.block.markdown",
            "settings": {
                "foreground": "#6cbfa3ee"
            }
        },
        {
            "scope": "markup.heading",
            "settings": {
                "foreground": "#8260b3ee"
            }
        },
        {
            "scope": "markup.inline.raw",
            "settings": {
                "foreground": "#bab767ee"
            }
        },
        {
            "scope": "markup.inserted",
            "settings": {
                "foreground": "#5478a7ee"
            }
        },
        {
            "scope": "markup.italic",
            "settings": {
                "foreground": "#b96f66ee"
            }
        },
        {
            "scope": "markup.raw.block.markdown",
            "settings": {
                "foreground": "#7599c8ee"
            }
        },
        {
            "scope": "markup.strikethrough",
            "settings": {
                "foreground": "#c16eaaee"
            }
        },
        {
            "scope": "markup.underline",
            "settings": {
                "foreground": "#c77d74ee"
            }
        },
        {
            "scope": "meta.block.c",
            "settings": {
                "foreground": "#c0766dee"
            }
        },
        {
            "scope": "meta.class.java",
            "settings": {
                "foreground": "#698dbcee"
            }
        },
        {
            "scope": "meta.definition.variable.name",
            "settings": {
                "foreground": "#5fb296ee"
            }
        },
        {
            "scope": "meta.diff.header",
            "settings": {
                "foreground": "#7b9fceee"
            }
        },
        {
            "scope": "meta.embedded",
            "settings": {
                "foreground": "#78bc69ee"
            }
        },
        {
            "scope": "meta.embedded.assembly",
            "settings": {
                "foreground": "#78bc69ee"
            }
        },
        {
            "scope": "meta.function-call.arguments.python",
            "settings": {
                "foreground": "#8f6dc0ee"
            }
        },
        {
            "scope": "meta.function-call.python",
            "settings": {
                "foreground": "#906ec1ee"
            }
        },
        {
            "scope": "meta.member.access.python",
            "settings": {
                "foreground": "#c8c575ee"
            }
        },
        {
            "scope": "meta.method.java",
            "settings": {
                "foreground": "#7957aaee"
            }
        },
        {
            "scope": "meta.object-literal.key",
            "settings": {
                "foreground": "#d0867dee"
            }
        },
        {
            "scope": "meta.paragraph.markdown",
            "settings": {
                "foreground": "#cd7ab6ee"
            }
        },
        {
            "scope": "meta.preprocessor",
            "settings": {
                "foreground": "#6cbfa3ee"
            }
        },
        {
            "scope": "meta.preprocessor.numeric",
            "settings": {
                "foreground": "#6d91c0ee"
            }
        },
        {
            "scope": "meta.preprocessor.string",
            "settings": {
                "foreground": "#d0867dee"
            }
        },
        {
            "scope": "meta.scope.prerequisites.makefile",
            "settings": {
                "foreground": "#79bd6aee"
            }
        },
        {
            "scope": "meta.structure.dictionary.json.comments",
            "settings": {
                "foreground": "#dddddd4e"
            }
        },
        {
            "scope": "meta.structure.dictionary.key.python",
            "settings": {
                "foreground": "#68ac59ee"
            }
        },
        {
            "scope": "meta.structure.dictionary.value.json.comments",
            "settings": {
                "foreground": "#e5e5e54e"
            }
        },
        {
            "scope": "meta.template.expression",
            "settings": {
                "foreground": "#9371c4ee"
            }
        },
        {
            "scope": "meta.type.cast.expr",
            "settings": {
                "foreground": "#c471adee"
            }
        },
        {
            "scope": "meta.type.new.expr",
            "settings": {
                "foreground": "#a6538fee"
            }
        },
        {
            "scope": "parameter",
            "settings": {
                "foreground": "#b2af5fee"
            }
        },
        {
            "scope": "punctuation.character.set.begin.regexp",
            "settings": {
                "foreground": "#dddddd4e"
            }
        },
        {
            "scope": "punctuation.character.set.end.regexp",
            "settings": {
                "foreground": "#e5e5e54e"
            }
        },
        {
            "scope": "punctuation.definition.character-class.regexp",
            "settings": {
                "foreground": "#e5e5e54e"
            }
        },
        {
            "scope": "punctuation.definition.comment",
            "settings": {
                "foreground": "#e1e1e14e"
            }
        },
        {
            "scope": "punctuation.definition.comment.json.comments",
            "settings": {
                "foreground": "#e9e9e94e"
            }
        },
        {
            "scope": "punctuation.definition.comment.python",
            "settings": {
                "foreground": "#e1e1e14e"
            }
        },
        {
            "scope": "punctuation.definition.dictionary.end.json",
            "settings": {
                "foreground": "#e9e9e94e"
            }
        },
        {
            "scope": "punctuation.definition.group.assertion.regexp",
            "settings": {
                "foreground": "#e5e5e54e"
            }
        },
        {
            "scope": "punctuation.definition.group.regexp",
            "settings": {
                "foreground": "#dddddd4e"
            }
        },
        {
            "scope": "punctuation.definition.list.begin.markdown",
            "settings": {
                "foreground": "#e5e5e54e"
            }
        },
        {
            "scope": "punctuation.definition.parameters.begin.python",
            "settings": {
                "foreground": "#e5e5e54e"
            }
        },
        {
            "scope": "punctuation.definition.quote.begin.markdown",
            "settings": {
                "foreground": "#e1e1e14e"
            }
        },
        {
            "scope": "punctuation.definition.tag",
            "settings": {
                "foreground": "#dddddd4e"
            }
        },
        {
            "scope": "punctuation.definition.template-expression.begin",
            "settings": {
                "foreground": "#dddddd4e"
            }
        },
        {
            "scope": "punctuation.definition.template-expression.end",
            "settings": {
                "foreground": "#e1e1e14e"
            }
        },
        {
            "scope": "punctuation.section.embedded",
            "settings": {
                "foreground": "#e9e9e94e"
            }
        },
        {
            "scope": "punctuation.section.embedded.begin.php",
            "settings": {
                "foreground": "#e1e1e14e"
            }
        },
        {
            "scope": "punctuation.section.embedded.end.php",
            "settings": {
                "foreground": "#e5e5e54e"
            }
        },
        {
            "scope": "punctuation.terminator.java",
            "settings": {
                "foreground": "#e5e5e54e"
            }
        },
        {
            "scope": "source.cmake",
            "settings": {
                "foreground": "#8ed27fee"
            }
        },
        {
            "scope": "source.coffee.embedded",
            "settings": {
                "foreground": "#8f6dc0ee"
            }
        },
        {
            "scope": "source.cpp",
            "settings": {
                "foreground": "#bab767ee"
            }
        },
        {
            "scope": "source.css.less",
            "settings": {
                "foreground": "#c0bd6dee"
            }
        },
        {
            "scope": "source.groovy.embedded",
            "settings": {
                "foreground": "#5a7eadee"
            }
        },
        {
            "scope": "source.java",
            "settings": {
                "foreground": "#bf756cee"
            }
        },
        {
            "scope": "source.java-properties",
            "settings": {
                "foreground": "#70c3a7ee"
            }
        },
        {
            "scope": "source.json.comments",
            "settings": {
                "foreground": "#e9e9e94e"
            }
        },
        {
            "scope": "source.makefile",
            "settings": {
                "foreground": "#bdba6aee"
            }
        },
        {
            "scope": "source.powershell",
            "settings": {
                "foreground": "#c976b2ee"
            }
        },
        {
            "scope": "source.powershell.variable.other.member",
            "settings": {
                "foreground": "#ccc979ee"
            }
        },
        {
            "scope": "source.python",
            "settings": {
                "foreground": "#ae5b97ee"
            }
        },
        {
            "scope": "storage",
            "settings": {
                "foreground": "#80c471ee"
            }
        },
        {
            "scope": "storage.modifier",
            "settings": {
                "foreground": "#5fb296ee"
            }
        },
        {
            "scope": "storage.modifier.import.java",
            "settings": {
                "foreground": "#b8b565ee"
            }
        },
        {
            "scope": "storage.modifier.package.java",
            "settings": {
                "foreground": "#815fb2ee"
            }
        },
        {
            "scope": "storage.type",
            "settings": {
                "foreground": "#bf756cee"
            }
        },
        {
            "scope": "storage.type.annotation.groovy",
            "settings": {
                "foreground": "#c1776eee"
            }
        },
        {
            "scope": "storage.type.annotation.java",
            "settings": {
                "foreground": "#c5c272ee"
            }
        },
        {
            "scope": "storage.type.boolean.go",
            "settings": {
                "foreground": "#aba858ee"
            }
        },
        {
            "scope": "storage.type.byte.go",
            "settings": {
                "foreground": "#7fc370ee"
            }
        },
        {
            "scope": "storage.type.cs",
            "settings": {
                "foreground": "#d17ebaee"
            }
        },
        {
            "scope": "storage.type.error.go",
            "settings": {
                "foreground": "#77caaeee"
            }
        },
        {
            "scope": "storage.type.generic.cs",
            "settings": {
                "foreground": "#b966a2ee"
            }
        },
        {
            "scope": "storage.type.generic.groovy",
            "settings": {
                "foreground": "#6a8ebdee"
            }
        },
        {
            "scope": "storage.type.generic.java",
            "settings": {
                "foreground": "#7acdb1ee"
            }
        },
        {
            "scope": "storage.type.groovy",
            "settings": {
                "foreground": "#b0ad5dee"
            }
        },
        {
            "scope": "storage.type.java",
            "settings": {
                "foreground": "#b9b666ee"
            }
        },
        {
            "scope": "storage.type.modifier.cs",
            "settings": {
                "foreground": "#6bbea2ee"
            }
        },
        {
            "scope": "storage.type.numeric.go",
            "settings": {
                "foreground": "#84c875ee"
            }
        },
        {
            "scope": "storage.type.object.array.groovy",
            "settings": {
                "foreground": "#7fd2b6ee"
            }
        },
        {
            "scope": "storage.type.object.array.java",
            "settings": {
                "foreground": "#597dacee"
            }
        },
        {
            "scope": "storage.type.parameters.groovy",
            "settings": {
                "foreground": "#ae645bee"
            }
        },
        {
            "scope": "storage.type.primitive.array.groovy",
            "settings": {
                "foreground": "#b3609cee"
            }
        },
        {
            "scope": "storage.type.primitive.array.java",
            "settings": {
                "foreground": "#b7b464ee"
            }
        },
        {
            "scope": "storage.type.primitive.groovy",
            "settings": {
                "foreground": "#72c5a9ee"
            }
        },
        {
            "scope": "storage.type.primitive.java",
            "settings": {
                "foreground": "#5aad91ee"
            }
        },
        {
            "scope": "storage.type.rune.go",
            "settings": {
                "foreground": "#7a58abee"
            }
        },
        {
            "scope": "storage.type.string.go",
            "settings": {
                "foreground": "#69bca0ee"
            }
        },
        {
            "scope": "storage.type.token.java",
            "settings": {
                "foreground": "#7da1d0ee"
            }
        },
        {
            "scope": "storage.type.uintptr.go",
            "settings": {
                "foreground": "#c47a71ee"
            }
        },
        {
            "scope": "storage.type.variable.cs",
            "settings": {
                "foreground": "#53a68aee"
            }
        },
        {
            "scope": "string",
            "settings": {
                "foreground": "#8866b9ee"
            }
        },
        {
            "scope": "string.quoted.docstring.multi.python",
            "settings": {
                "foreground": "#e9e9e94e"
            }
        },
        {
            "scope": "string.regexp",
            "settings": {
                "foreground": "#65b89cee"
            }
        },
        {
            "scope": "string.tag",
            "settings": {
                "foreground": "#c2786fee"
            }
        },
        {
            "scope": "string.value",
            "settings": {
                "foreground": "#b66c63ee"
            }
        },
        {
            "scope": "strong",
            "settings": {
                "foreground": "#7599c8ee"
            }
        },
        {
            "scope": "support.class",
            "settings": {
                "foreground": "#5a7eadee"
            }
        },
        {
            "scope": "support.constant.color",
            "settings": {
                "foreground": "#cd837aee"
            }
        },
        {
            "scope": "support.constant.dom",
            "settings": {
                "foreground": "#66aa57ee"
            }
        },
        {
            "scope": "support.constant.font-name",
            "settings": {
                "foreground": "#74b865ee"
            }
        },
        {
            "scope": "support.constant.handlebars",
            "settings": {
                "foreground": "#64a855ee"
            }
        },
        {
            "scope": "support.constant.json",
            "settings": {
                "foreground": "#61b498ee"
            }
        },
        {
            "scope": "support.constant.math",
            "settings": {
                "foreground": "#b5629eee"
            }
        },
        {
            "scope": "support.constant.media",
            "settings": {
                "foreground": "#c0bd6dee"
            }
        },
        {
            "scope": "support.constant.media-type",
            "settings": {
                "foreground": "#63a754ee"
            }
        },
        {
            "scope": "support.constant.property-value",
            "settings": {
                "foreground": "#7bceb2ee"
            }
        },
        {
            "scope": "support.function",
            "settings": {
                "foreground": "#b66c63ee"
            }
        },
        {
            "scope": "support.function.git-rebase",
            "settings": {
                "foreground": "#67ba9eee"
            }
        },
        {
            "scope": "support.other.parenthesis.regexp",
            "settings": {
                "foreground": "#aa6057ee"
            }
        },
        {
            "scope": "support.type",
            "settings": {
                "foreground": "#adaa5aee"
            }
        },
        {
            "scope": "support.type.property-name",
            "settings": {
                "foreground": "#c16eaaee"
            }
        },
        {
            "scope": "support.type.vendored.property-name",
            "settings": {
                "foreground": "#c2786fee"
            }
        },
        {
            "scope": "support.variable",
            "settings": {
                "foreground": "#70c3a7ee"
            }
        },
        {
            "scope": "token.debug-token",
            "settings": {
                "foreground": "#b4b161ee"
            }
        },
        {
            "scope": "token.error-token",
            "settings": {
                "foreground": "#85c976ee"
            }
        },
        {
            "scope": "token.info-token",
            "settings": {
                "foreground": "#7dc16eee"
            }
        },
        {
            "scope": "token.warn-token",
            "settings": {
                "foreground": "#9b79ccee"
            }
        },
        {
            "scope": "variable",
            "settings": {
                "foreground": "#77bb68ee"
            }
        },
        {
            "scope": "variable.css",
            "settings": {
                "foreground": "#ac5995ee"
            }
        },
        {
            "scope": "variable.language",
            "settings": {
                "foreground": "#67ba9eee"
            }
        },
        {
            "scope": "variable.language.wildcard.java",
            "settings": {
                "foreground": "#bb7168ee"
            }
        },
        {
            "scope": "variable.other.constant",
            "settings": {
                "foreground": "#7b59acee"
            }
        },
        {
            "scope": "variable.other.definition.java",
            "settings": {
                "foreground": "#d0cd7dee"
            }
        },
        {
            "scope": "variable.other.enummember",
            "settings": {
                "foreground": "#d0867dee"
            }
        },
        {
            "scope": "variable.other.less",
            "settings": {
                "foreground": "#75b966ee"
            }
        },
        {
            "scope": "variable.other.object.java",
            "settings": {
                "foreground": "#cc8279ee"
            }
        },
        {
            "scope": "variable.other.object.property.java",
            "settings": {
                "foreground": "#58ab8fee"
            }
        },
        {
            "scope": "variable.parameter.c",
            "settings": {
                "foreground": "#8ace7bee"
            }
        },
        {
            "scope": "variable.parameter.function.language.python",
            "settings": {
                "foreground": "#6baf5cee"
            }
        },
        {
            "scope": "variable.parameter.java",
            "settings": {
                "foreground": "#9d7bceee"
            }
        },
        {
            "scope": "variable.scss",
            "settings": {
                "foreground": "#b2685fee"
            }
        }
    ]
}