{
    "$schema": "vscode://schemas/color-theme",
    "type": "dark",
    "colors": {
        "actionBar.toggledBackground": "#0e0d10fe",
        "activityBar.activeBackground": "#0e0d10fe",
        "activityBar.activeBorder": "#a7c7d5de",
        "activityBar.activeFocusBorder": "#05080800",
        "activityBar.background": "#060508fe",
        "activityBar.border": "#06050800",
        "activityBar.dropBorder": "#7a797c43",
        "activityBar.foreground": "#adcddbde",
        "activityBar.inactiveForeground": "#68656685",
        "activityBarBadge.background": "#7a7a00fe",
        "activityBarBadge.foreground": "#060508fe",
        "badge.background": "#7a7a00fe",
        "badge.foreground": "#060508fe",
        "banner.background": "#0e0d10fe",
        "banner.foreground": "#c7c8c5c4",
        "banner.iconForeground": "#875987fe",
        "breadcrumb.activeSelectionForeground": "#97b7c5ca",
        "breadcrumb.background": "#68656682",
        "breadcrumb.focusForeground": "#bdc0c0c5",
        "breadcrumb.foreground": "#f4f4f4be",
        "breadcrumbPicker.background": "#0e0d10fe",
        "button.background": "#0e0d10fe",
        "button.border": "#abcbd9de",
        "button.foreground": "#d8d5d6c7",
        "button.hoverBackground": "#0e0d10fe",
        "button.secondaryBackground": "#0e0d10fe",
        "button.secondaryForeground": "#cac9ccc3",
        "button.secondaryHoverBackground": "#0e0d10fe",
        "button.separator": "#bdc0c0fc",
        "charts.blue": "#4d4dffc0",
        "charts.foreground": "#d3d4d1c2",
        "charts.green": "#004000cb",
        "charts.lines": "#9b6d9bf2",
        "charts.orange": "#ffba22ce",
        "charts.purple": "#670067c9",
        "charts.red": "#400000cb",
        "charts.yellow": "#e6e600ce",
        "chat.requestBorder": "#7a797c45",
        "chat.slashCommandBackground": "#0e0d10fe",
        "chat.slashCommandForeground": "#bcb9bac4",
        "checkbox.background": "#0e0d10fe",
        "checkbox.border": "#7a797c43",
        "checkbox.foreground": "#bfc0bdc7",
        "checkbox.selectBackground": "#8b85b341",
        "checkbox.selectBorder": "#7a797c46",
        "commandCenter.activeBackground": "#83b19541",
        "commandCenter.activeBorder": "#7a797c43",
        "commandCenter.activeForeground": "#c0bdbec7",
        "commandCenter.background": "#0e0d10fe",
        "commandCenter.border": "#7a797c47",
        "commandCenter.foreground": "#bcb9bac7",
        "commandCenter.inactiveBorder": "#4e4d5022",
        "commandCenter.inactiveForeground": "#68656681",
        "commentsView.resolvedIcon": "#00cc00cb",
        "commentsView.unresolvedIcon": "#00cc00cb",
        "contrastActiveBorder": "#08050600",
        "contrastBorder": "#05080800",
        "debugConsole.errorForeground": "#cc00ffce",
        "debugConsole.infoForeground": "#dde0e0c6",
        "debugConsole.sourceForeground": "#dedde0c1",
        "debugConsole.warningForeground": "#e6e600ce",
        "debugConsoleInputIcon.foreground": "#afcfddde",
        "debugExceptionWidget.background": "#670067b0",
        "debugExceptionWidget.border": "#7a797c42",
        "debugIcon.breakpointCurrentStackframeForeground": "#5d5785fe",
        "debugIcon.breakpointDisabledForeground": "#716b99fe",
        "debugIcon.breakpointForeground": "#8dadbbfe",
        "debugIcon.breakpointStackframeForeground": "#956795fe",
        "debugIcon.breakpointUnverifiedForeground": "#cb9da4fe",
        "debugIcon.continueForeground": "#d7a9b0fe",
        "debugIcon.disconnectForeground": "#a59fcdfe",
        "debugIcon.pauseForeground": "#a577a5fe",
        "debugIcon.restartForeground": "#958fbdfe",
        "debugIcon.startForeground": "#a1c1cffe",
        "debugIcon.stepBackForeground": "#6d6795fe",
        "debugIcon.stepIntoForeground": "#837dabfe",
        "debugIcon.stepOutForeground": "#cbbd9dfe",
        "debugIcon.stepOverForeground": "#734573fe",
        "debugIcon.stopForeground": "#597987fe",
        "debugTokenExpression.boolean": "#61818ffa",
        "debugTokenExpression.error": "#77a589f6",
        "debugTokenExpression.name": "#252828ee",
        "debugTokenExpression.number": "#878885f0",
        "debugTokenExpression.string": "#b5e3c7fa",
        "debugTokenExpression.value": "#517f63f4",
        "debugToolBar.background": "#670067b1",
        "debugToolBar.border": "#7a797c43",
        "debugView.exceptionLabelBackground": "#670067bb",
        "debugView.exceptionLabelForeground": "#c1c4c4c4",
        "debugView.stateLabelBackground": "#670067c4",
        "debugView.stateLabelForeground": "#d1d4d4c4",
        "debugView.valueChangedHighlight": "#7f9fad41",
        "descriptionForeground": "#c0bdbec7",
        "diffEditor.border": "#07080500",
        "diffEditor.diagonalFill": "#7f807df3",
        "diffEditor.insertedLineBackground": "#9aff9a21",
        "diffEditor.insertedTextBackground": "#004000cb",
        "diffEditor.insertedTextBorder": "#08050600",
        "diffEditor.move.border": "#08050600",
        "diffEditor.moveActive.border": "#08050600",
        "diffEditor.removedLineBackground": "#ff9a9a21",
        "diffEditor.removedTextBackground": "#400000cb",
        "diffEditor.removedTextBorder": "#06050800",
        "diffEditor.unchangedCodeBackground": "#121114fe",
        "diffEditor.unchangedRegionBackground": "#121114fe",
        "diffEditor.unchangedRegionForeground": "#c6c5c8c4",
        "diffEditorGutter.insertedLineBackground": "#004000cb",
        "diffEditorGutter.removedLineBackground": "#400000cb",
        "diffEditorOverview.insertedForeground": "#00cc00cb",
        "diffEditorOverview.removedForeground": "#ff5050cb",
        "disabledForeground": "#68656687",
        "dropdown.background": "#0e0d10fe",
        "dropdown.border": "#7a797c42",
        "dropdown.foreground": "#c7c8c5c7",
        "dropdown.listBackground": "#0e0d10fe",
        "editor.background": "#121114fe",
        "editor.findMatchBackground": "#7dab8f41",
        "editor.findMatchBorder": "#8ca57741",
        "editor.findMatchHighlightBackground": "#7d77a541",
        "editor.findMatchHighlightBorder": "#b1838a41",
        "editor.findRangeHighlightBackground": "#a3957541",
        "editor.findRangeHighlightBorder": "#9cb58741",
        "editor.focusedStackFrameHighlightBackground": "#857fad41",
        "editor.foldBackground": "#ab9d7d41",
        "editor.foreground": "#c0bdbec5",
        "editor.hoverHighlightBackground": "#7fad9141",
        "editor.inactiveSelectionBackground": "#83b19541",
        "editor.inlineValuesBackground": "#121114fe",
        "editor.inlineValuesForeground": "#bbbcb9c2",
        "editor.lineHighlightBackground": "#87a7b541",
        "editor.lineHighlightBorder": "#08050600",
        "editor.linkedEditingBackground": "#121114fe",
        "editor.rangeHighlightBackground": "#81a1af41",
        "editor.rangeHighlightBorder": "#ab9d7d41",
        "editor.selectionBackground": "#b3a58541",
        "editor.selectionForeground": "#5a7345ca",
        "editor.selectionHighlightBackground": "#b1a38341",
        "editor.selectionHighlightBorder": "#ab7d8441",
        "editor.snippetFinalTabstopHighlightBackground": "#92ab7d41",
        "editor.snippetFinalTabstopHighlightBorder": "#a3957541",
        "editor.snippetTabstopHighlightBackground": "#a5977741",
        "editor.snippetTabstopHighlightBorder": "#79a78b41",
        "editor.stackFrameHighlightBackground": "#9cb58741",
        "editor.symbolHighlightBackground": "#af818841",
        "editor.symbolHighlightBorder": "#7dab8f41",
        "editor.wordHighlightBackground": "#b3858c41",
        "editor.wordHighlightBorder": "#b5a78741",
        "editor.wordHighlightStrongBackground": "#90a97b41",
        "editor.wordHighlightStrongBorder": "#ffba22ce",
        "editor.wordHighlightTextBackground": "#7797a541",
        "editor.wordHighlightTextBorder": "#a375a341",
        "editorBracketHighlight.foreground1": "#7b75a341",
        "editorBracketHighlight.foreground2": "#b3858c41",
        "editorBracketHighlight.foreground3": "#87b59941",
        "editorBracketHighlight.foreground4": "#a97b8241",
        "editorBracketHighlight.foreground5": "#7d9dab41",
        "editorBracketHighlight.foreground6": "#ab7d8441",
        "editorBracketHighlight.unexpectedBracket.foreground": "#b3a58541",
        "editorBracketMatch.background": "#94ad7f41",
        "editorBracketMatch.border": "#a7798041",
        "editorBracketPairGuide.activeBackground1": "#92ab7d41",
        "editorBracketPairGuide.activeBackground2": "#b385b341",
        "editorBracketPairGuide.activeBackground3": "#ad9f7f41",
        "editorBracketPairGuide.activeBackground4": "#ad7f8641",
        "editorBracketPairGuide.activeBackground5": "#7d9dab41",
        "editorBracketPairGuide.activeBackground6": "#81a1af41",
        "editorBracketPairGuide.background1": "#121114fe",
        "editorBracketPairGuide.background2": "#121114fe",
        "editorBracketPairGuide.background3": "#121114fe",
        "editorBracketPairGuide.background4": "#121114fe",
        "editorBracketPairGuide.background5": "#121114fe",
        "editorBracketPairGuide.background6": "#121114fe",
        "editorCodeLens.foreground": "#595c5c75",
        "editorCommentsWidget.rangeActiveBackground": "#121114fe",
        "editorCommentsWidget.rangeBackground": "#121114fe",
        "editorCommentsWidget.resolvedBorder": "#7a797c47",
        "editorCommentsWidget.unresolvedBorder": "#ff5050cb",
        "editorCursor.background": "#121114fe",
        "editorCursor.foreground": "#7a7a00fe",
        "editorError.background": "#08050600",
        "editorError.border": "#07080500",
        "editorError.foreground": "#cc00ffce",
        "editorGhostText.background": "#121114fe",
        "editorGhostText.border": "#08050600",
        "editorGhostText.foreground": "#aaa9ac77",
        "editorGroup.border": "#7a797c44",
        "editorGroup.dropBackground": "#121114fe",
        "editorGroup.dropIntoPromptBackground": "#121114fe",
        "editorGroup.dropIntoPromptBorder": "#7a797c47",
        "editorGroup.dropIntoPromptForeground": "#d6d5d8c7",
        "editorGroup.emptyBackground": "#121114fe",
        "editorGroup.focusedEmptyBorder": "#7a797c45",
        "editorGroupHeader.border": "#06050800",
        "editorGroupHeader.noTabsBackground": "#121114fe",
        "editorGroupHeader.tabsBackground": "#121114fe",
        "editorGroupHeader.tabsBorder": "#06050800",
        "editorGutter.addedBackground": "#00cc00cb",
        "editorGutter.background": "#121114fe",
        "editorGutter.commentGlyphForeground": "#c8c5c6c1",
        "editorGutter.commentRangeForeground": "#c9ccccc7",
        "editorGutter.commentUnresolvedGlyphForeground": "#00cc00cb",
        "editorGutter.deletedBackground": "#ff5050cb",
        "editorGutter.foldingControlForeground": "#b1a38341",
        "editorGutter.modifiedBackground": "#ffba22ce",
        "editorHint.border": "#06050800",
        "editorHint.foreground": "#4d4dffc5",
        "editorHoverWidget.background": "#0e0d10fe",
        "editorHoverWidget.border": "#7a797c47",
        "editorHoverWidget.foreground": "#75a387fe",
        "editorHoverWidget.highlightForeground": "#b98bb9ca",
        "editorHoverWidget.statusBarBackground": "#121114fe",
        "editorIndentGuide.activeBackground1": "#7a7a00fe",
        "editorIndentGuide.activeBackground2": "#7a7a00fe",
        "editorIndentGuide.activeBackground3": "#7a7a00fe",
        "editorIndentGuide.activeBackground4": "#7a7a00fe",
        "editorIndentGuide.activeBackground5": "#7a7a00fe",
        "editorIndentGuide.activeBackground6": "#7a7a00fe",
        "editorIndentGuide.background1": "#a7798041",
        "editorIndentGuide.background2": "#a375a341",
        "editorIndentGuide.background3": "#79a78b41",
        "editorIndentGuide.background4": "#7999a741",
        "editorIndentGuide.background5": "#7d9dab41",
        "editorIndentGuide.background6": "#ad7fad41",
        "editorInfo.background": "#08050600",
        "editorInfo.border": "#08050600",
        "editorInfo.foreground": "#4d4dffc8",
        "editorInlayHint.background": "#121114fe",
        "editorInlayHint.foreground": "#c3c4c1c1",
        "editorInlayHint.parameterBackground": "#121114fe",
        "editorInlayHint.parameterForeground": "#cecdd0c3",
        "editorInlayHint.typeBackground": "#121114fe",
        "editorInlayHint.typeForeground": "#c4c1c2c2",
        "editorLightBulb.foreground": "#ffba22ce",
        "editorLightBulbAutoFix.foreground": "#00cc00cb",
        "editorLineNumber.activeForeground": "#7a7a00fe",
        "editorLineNumber.dimmedForeground": "#4241447d",
        "editorLineNumber.foreground": "#8d90907c",
        "editorLink.activeForeground": "#ffba22ce",
        "editorMarkerNavigation.background": "#121114fe",
        "editorMarkerNavigationError.background": "#670067b0",
        "editorMarkerNavigationError.headerBackground": "#670067bd",
        "editorMarkerNavigationInfo.background": "#4d4dffa7",
        "editorMarkerNavigationInfo.headerBackground": "#4d4dffae",
        "editorMarkerNavigationWarning.background": "#7a7a00fe",
        "editorMarkerNavigationWarning.headerBackground": "#7a7a00fe",
        "editorOverviewRuler.addedForeground": "#00cc00cb",
        "editorOverviewRuler.background": "#060508fe",
        "editorOverviewRuler.border": "#060508fe",
        "editorOverviewRuler.bracketMatchForeground": "#060508fe",
        "editorOverviewRuler.commentForeground": "#060508fe",
        "editorOverviewRuler.commentUnresolvedForeground": "#060508fe",
        "editorOverviewRuler.commonContentForeground": "#060508fe",
        "editorOverviewRuler.currentContentForeground": "#cececebd",
        "editorOverviewRuler.deletedForeground": "#ff5050cb",
        "editorOverviewRuler.errorForeground": "#cc00ffce",
        "editorOverviewRuler.findMatchForeground": "#00a5a5c0",
        "editorOverviewRuler.incomingContentForeground": "#00cc00cb",
        "editorOverviewRuler.infoForeground": "#4d4dffaa",
        "editorOverviewRuler.modifiedForeground": "#ffba22ce",
        "editorOverviewRuler.rangeHighlightForeground": "#060508fe",
        "editorOverviewRuler.selectionHighlightForeground": "#4d4dffc5",
        "editorOverviewRuler.warningForeground": "#060508fe",
        "editorOverviewRuler.wordHighlightForeground": "#060508fe",
        "editorOverviewRuler.wordHighlightStrongForeground": "#060508fe",
        "editorOverviewRuler.wordHighlightTextForeground": "#060508fe",
        "editorPane.background": "#121114fe",
        "editorRuler.foreground": "#ad7f8641",
        "editorStickyScroll.background": "#121114fe",
        "editorStickyScrollHover.background": "#121114fe",
        "editorSuggestWidget.background": "#0e0d10fe",
        "editorSuggestWidget.border": "#7a797c47",
        "editorSuggestWidget.focusHighlightForeground": "#b5afddfe",
        "editorSuggestWidget.foreground": "#afddc1fe",
        "editorSuggestWidget.highlightForeground": "#95b5c3ca",
        "editorSuggestWidget.selectedBackground": "#a3757c41",
        "editorSuggestWidget.selectedForeground": "#abd9bdca",
        "editorSuggestWidget.selectedIconForeground": "#b8d1a3ca",
        "editorSuggestWidgetStatus.foreground": "#c799c7fe",
        "editorUnicodeHighlight.background": "#79a78b41",
        "editorUnicodeHighlight.border": "#8ea77941",
        "editorUnnecessaryCode.border": "#bc5a00fe",
        "editorUnnecessaryCode.opacity": "#bc5a00fe",
        "editorWarning.background": "#07080500",
        "editorWarning.border": "#07080500",
        "editorWarning.foreground": "#e6e600ce",
        "editorWhitespace.foreground": "#c0bdbec3",
        "editorWidget.background": "#121114fe",
        "editorWidget.border": "#7a797c43",
        "editorWidget.foreground": "#c1c4c4c6",
        "editorWidget.resizeBorder": "#7a797c41",
        "errorForeground": "#cc00ffce",
        "extensionBadge.remoteBackground": "#7a7a00fe",
        "extensionBadge.remoteForeground": "#060508fe",
        "extensionButton.background": "#0e0d10fe",
        "extensionButton.foreground": "#c4c1c2c2",
        "extensionButton.hoverBackground": "#0e0d10fe",
        "extensionButton.prominentBackground": "#0e0d10fe",
        "extensionButton.prominentForeground": "#bbbcb9c5",
        "extensionButton.prominentHoverBackground": "#0e0d10fe",
        "extensionButton.separator": "#615b89f2",
        "extensionIcon.preReleaseForeground": "#abd9bdfe",
        "extensionIcon.sponsorForeground": "#8f8161fe",
        "extensionIcon.starForeground": "#8b85b3fe",
        "extensionIcon.verifiedForeground": "#476775fe",
        "focusBorder": "#07080500",
        "foreground": "#c2c1c4c1",
        "gitDecoration.addedResourceForeground": "#00cc00cb",
        "gitDecoration.deletedResourceForeground": "#ff5050cb",
        "gitDecoration.modifiedResourceForeground": "#ffba22ce",
        "gitDecoration.renamedResourceForeground": "#84a3f9ba",
        "gitDecoration.stageDeletedResourceForeground": "#ff5050cb",
        "gitDecoration.stageModifiedResourceForeground": "#00cc00cb",
        "gitDecoration.untrackedResourceForeground": "#00a5a5a6",
        "icon.foreground": "#abcbd9de",
        "inlineChat.background": "#0e0d10fe",
        "inlineChat.border": "#7a797c45",
        "inlineChat.regionHighlight": "#b587b541",
        "inlineChat.shadow": "#07080500",
        "inlineChatDiff.inserted": "#edf0f0f7",
        "inlineChatDiff.removed": "#9ab385fd",
        "inlineChatInput.background": "#333333b3",
        "inlineChatInput.border": "#7a797c46",
        "inlineChatInput.focusBorder": "#08050600",
        "inlineChatInput.placeholderForeground": "#bcb9bac5",
        "input.background": "#333333a8",
        "input.border": "#7a797c45",
        "input.foreground": "#d4d1d2c1",
        "input.placeholderForeground": "#c4c1c2c2",
        "inputOption.activeBackground": "#7b75a341",
        "inputOption.activeBorder": "#7a797c45",
        "inputOption.activeForeground": "#d1d4d4c6",
        "inputOption.hoverBackground": "#0e0d10fe",
        "inputValidation.errorBackground": "#670067c2",
        "inputValidation.errorBorder": "#670067aa",
        "inputValidation.errorForeground": "#cc00ffce",
        "inputValidation.infoBackground": "#4d4dffa3",
        "inputValidation.infoBorder": "#7a797c42",
        "inputValidation.infoForeground": "#d5d8d8c6",
        "inputValidation.warningBackground": "#7a7a00fe",
        "inputValidation.warningBorder": "#7a797c45",
        "inputValidation.warningForeground": "#e6e600ce",
        "interactive.activeCodeBorder": "#7a797c44",
        "interactive.inactiveCodeBorder": "#4e4d5027",
        "keybindingLabel.background": "#0e0d10fe",
        "keybindingLabel.border": "#7a797c42",
        "keybindingLabel.bottomBorder": "#7a797c44",
        "keybindingLabel.foreground": "#ccc9cac4",
        "keybindingTable.headerBackground": "#0e0d10fe",
        "keybindingTable.rowsBackground": "#0e0d10fe",
        "list.activeSelectionBackground": "#7797a541",
        "list.activeSelectionForeground": "#73a185ca",
        "list.activeSelectionIconForeground": "#b3d3e1ca",
        "list.deemphasizedForeground": "#d6d5d8c6",
        "list.dropBackground": "#0e0d10fe",
        "list.errorForeground": "#cc00ffce",
        "list.filterMatchBackground": "#0e0d10fe",
        "list.filterMatchBorder": "#7a797c44",
        "list.focusAndSelectionOutline": "#ab7d8441",
        "list.focusBackground": "#a99b7b41",
        "list.focusForeground": "#d0cdcec3",
        "list.focusHighlightForeground": "#ad7f86fe",
        "list.focusOutline": "#817ba941",
        "list.highlightForeground": "#647d4fca",
        "list.hoverBackground": "#87a7b541",
        "list.hoverForeground": "#c4ddaffe",
        "list.inactiveFocusBackground": "#4e4d5025",
        "list.inactiveFocusOutline": "#ad7fad41",
        "list.inactiveSelectionBackground": "#060508fe",
        "list.inactiveSelectionForeground": "#abd9bdca",
        "list.inactiveSelectionIconForeground": "#748d5fca",
        "list.invalidItemForeground": "#c9ccccc2",
        "list.warningForeground": "#e6e600ce",
        "listFilterWidget.background": "#0e0d10fe",
        "listFilterWidget.noMatchesOutline": "#7999a741",
        "listFilterWidget.outline": "#81a1af41",
        "listFilterWidget.shadow": "#06050800",
        "menu.background": "#060508fe",
        "menu.border": "#7a797c45",
        "menu.foreground": "#adcddbde",
        "menu.selectionBackground": "#81a1af41",
        "menu.selectionBorder": "#7a797c43",
        "menu.selectionForeground": "#7f9fadca",
        "menu.separatorBackground": "#a9c9d7de",
        "menubar.selectionBackground": "#8781af41",
        "menubar.selectionBorder": "#7a797c47",
        "menubar.selectionForeground": "#95676eca",
        "merge.border": "#7a797c46",
        "merge.commonContentBackground": "#0e0d10fe",
        "merge.commonHeaderBackground": "#0e0d10fe",
        "merge.currentContentBackground": "#9aff9a21",
        "merge.currentHeaderBackground": "#004000cb",
        "merge.incomingContentBackground": "#00cc00cb",
        "merge.incomingHeaderBackground": "#004000cb",
        "mergeEditor.change.background": "#121114fe",
        "mergeEditor.change.word.background": "#121114fe",
        "mergeEditor.changeBase.background": "#121114fe",
        "mergeEditor.changeBase.word.background": "#121114fe",
        "mergeEditor.conflict.handled.minimapOverViewRuler": "#b789b7f7",
        "mergeEditor.conflict.handledFocused.border": "#7a797c46",
        "mergeEditor.conflict.handledUnfocused.border": "#4e4d5024",
        "mergeEditor.conflict.input1.background": "#121114fe",
        "mergeEditor.conflict.input2.background": "#121114fe",
        "mergeEditor.conflict.unhandled.minimapOverViewRuler": "#7fad91f2",
        "mergeEditor.conflict.unhandledFocused.border": "#7a797c47",
        "mergeEditor.conflict.unhandledUnfocused.border": "#4e4d5022",
        "mergeEditor.conflictingLines.background": "#121114fe",
        "minimap.background": "#0e0d10fe",
        "minimap.errorHighlight": "#cc00ffce",
        "minimap.findMatchHighlight": "#00a5a5b5",
        "minimap.foregroundOpacity": "#c8c5c6c6",
        "minimap.selectionHighlight": "#4d4dffa9",
        "minimap.selectionOccurrenceHighlight": "#84a3f99a",
        "minimap.warningHighlight": "#e6e600ce",
        "minimapGutter.addedBackground": "#00cc00cb",
        "minimapGutter.deletedBackground": "#400000cb",
        "minimapGutter.modifiedBackground": "#ffba22ce",
        "minimapSlider.activeBackground": "#a3957541",
        "minimapSlider.background": "#a9c9d7de",
        "minimapSlider.hoverBackground": "#7595a341",
        "notebook.cellBorderColor": "#7a797c43",
        "notebook.cellEditorBackground": "#121114fe",
        "notebook.cellHoverBackground": "#0e0d10fe",
        "notebook.cellInsertionIndicator": "#d3d4d1ef",
        "notebook.cellStatusBarItemHoverBackground": "#0e0d10fe",
        "notebook.cellToolbarSeparator": "#343132f8",
        "notebook.editorBackground": "#121114fe",
        "notebook.focusedCellBackground": "#060508fe",
        "notebook.focusedCellBorder": "#adcddbde",
        "notebook.focusedEditorBorder": "#7a797c44",
        "notebook.inactiveFocusedCellBorder": "#4e4d5024",
        "notebook.inactiveSelectedCellBorder": "#4e4d5021",
        "notebook.outputContainerBackgroundColor": "#0e0d10fe",
        "notebook.outputContainerBorderColor": "#7a797c43",
        "notebook.selectedCellBackground": "#87a7b541",
        "notebook.selectedCellBorder": "#7a797c43",
        "notebook.symbolHighlightBackground": "#96af8141",
        "notebookEditorOverviewRuler.runningCellForeground": "#060508fe",
        "notebookScrollbarSlider.activeBackground": "#b385b341",
        "notebookScrollbarSlider.background": "#a9c9d7de",
        "notebookScrollbarSlider.hoverBackground": "#b5a78741",
        "notebookStatusErrorIcon.foreground": "#a9c9d7de",
        "notebookStatusRunningIcon.foreground": "#a7c7d5de",
        "notebookStatusSuccessIcon.foreground": "#a7c7d5de",
        "notificationCenter.border": "#7a797c41",
        "notificationCenterHeader.background": "#0e0d10fe",
        "notificationCenterHeader.foreground": "#bebdc0c2",
        "notificationLink.foreground": "#c5c8c8c3",
        "notificationToast.border": "#7a797c44",
        "notifications.background": "#0e0d10fe",
        "notifications.border": "#7a797c45",
        "notifications.foreground": "#bcb9bac3",
        "notificationsErrorIcon.foreground": "#a7c7d5de",
        "notificationsInfoIcon.foreground": "#afcfddde",
        "notificationsWarningIcon.foreground": "#a7c7d5de",
        "panel.background": "#0e0d10fe",
        "panel.border": "#7a797c45",
        "panel.dropBorder": "#7a797c47",
        "panelInput.border": "#7a797c41",
        "panelSection.border": "#7a797c47",
        "panelSection.dropBackground": "#0e0d10fe",
        "panelSectionHeader.background": "#0e0d10fe",
        "panelSectionHeader.border": "#7a797c41",
        "panelSectionHeader.foreground": "#d7d8d5c4",
        "panelTitle.activeBorder": "#7a797c41",
        "panelTitle.activeForeground": "#a9c9d7de",
        "panelTitle.inactiveForeground": "#68656686",
        "peekView.border": "#7a797c42",
        "peekViewEditor.background": "#121114fe",
        "peekViewEditor.matchHighlightBackground": "#8ca57741",
        "peekViewEditor.matchHighlightBorder": "#8b85b341",
        "peekViewEditorGutter.background": "#121114fe",
        "peekViewEditorStickyScroll.background": "#121114fe",
        "peekViewResult.background": "#0e0d10fe",
        "peekViewResult.fileForeground": "#d3d4d1c7",
        "peekViewResult.lineForeground": "#c2c1c4c3",
        "peekViewResult.matchHighlightBackground": "#7f79a741",
        "peekViewResult.selectionBackground": "#83a3b141",
        "peekViewResult.selectionForeground": "#e5d7b7ca",
        "peekViewTitle.background": "#0e0d10fe",
        "peekViewTitleDescription.foreground": "#bab9bcc7",
        "peekViewTitleLabel.foreground": "#d3d4d1c7",
        "pickerGroup.border": "#7a797c47",
        "pickerGroup.foreground": "#dcd9dac6",
        "ports.iconRunningProcessForeground": "#9d6f76fe",
        "problemsErrorIcon.foreground": "#cc00ffce",
        "problemsInfoIcon.foreground": "#4d4dffb2",
        "problemsWarningIcon.foreground": "#e6e600ce",
        "profileBadge.background": "#7a7a00fe",
        "profileBadge.foreground": "#060508fe",
        "progressBar.background": "#0e0d10fe",
        "quickInput.background": "#0e0d10fe",
        "quickInput.foreground": "#a9c9d7de",
        "quickInputList.focusBackground": "#8781af41",
        "quickInputList.focusForeground": "#c9ccccc4",
        "quickInputList.focusIconForeground": "#7b4d54fe",
        "quickInputTitle.background": "#0e0d10fe",
        "sash.hoverBorder": "#7a797c41",
        "scrollbar.shadow": "#08050600",
        "scrollbarSlider.activeBackground": "#af818841",
        "scrollbarSlider.background": "#afcfddde",
        "scrollbarSlider.hoverBackground": "#817ba941",
        "search.resultsInfoForeground": "#bbbcb9c6",
        "searchEditor.findMatchBackground": "#a7798041",
        "searchEditor.findMatchBorder": "#7f9fad41",
        "searchEditor.textInputBorder": "#7a797c44",
        "selection.background": "#0e0d10fe",
        "settings.checkboxBackground": "#0e0d10fe",
        "settings.checkboxBorder": "#7a797c43",
        "settings.checkboxForeground": "#bfc0bdc4",
        "settings.dropdownBackground": "#0e0d10fe",
        "settings.dropdownBorder": "#7a797c43",
        "settings.dropdownForeground": "#dde0e0c4",
        "settings.dropdownListBorder": "#7a797c45",
        "settings.focusedRowBackground": "#837dab41",
        "settings.focusedRowBorder": "#7a797c46",
        "settings.headerBorder": "#7a797c46",
        "settings.headerForeground": "#dcd9dac6",
        "settings.modifiedItemIndicator": "#ffba22ce",
        "settings.numberInputBackground": "#0e0d10fe",
        "settings.numberInputBorder": "#7a797c47",
        "settings.numberInputForeground": "#bab9bcc2",
        "settings.rowHoverBackground": "#0e0d10fe",
        "settings.sashBorder": "#7a797c41",
        "settings.settingsHeaderHoverForeground": "#c597c5fe",
        "settings.textInputBackground": "#0e0d10fe",
        "settings.textInputBorder": "#7a797c46",
        "settings.textInputForeground": "#c6c5c8c2",
        "sideBar.background": "#0e0d10fe",
        "sideBar.border": "#7a797c41",
        "sideBar.dropBackground": "#0e0d10fe",
        "sideBar.foreground": "#dad9dcc5",
        "sideBarSectionHeader.background": "#06050800",
        "sideBarSectionHeader.border": "#7a797c41",
        "sideBarSectionHeader.foreground": "#cecdd0c2",
        "sideBarTitle.foreground": "#d0cdcec3",
        "sideBySideEditor.horizontalBorder": "#7a797c45",
        "sideBySideEditor.verticalBorder": "#7a797c46",
        "simpleFindWidget.sashBorder": "#7a797c43",
        "statusBar.background": "#0e0d10fe",
        "statusBar.border": "#7a797c42",
        "statusBar.debuggingBackground": "#670067b7",
        "statusBar.debuggingBorder": "#7a797c41",
        "statusBar.debuggingForeground": "#b9bcbcc4",
        "statusBar.focusBorder": "#08050600",
        "statusBar.foreground": "#ccc9cac6",
        "statusBar.noFolderBackground": "#0e0d10fe",
        "statusBar.noFolderBorder": "#7a797c47",
        "statusBar.noFolderForeground": "#c6c5c8c6",
        "statusBarItem.activeBackground": "#ab9d7d41",
        "statusBarItem.compactHoverBackground": "#0e0d10fe",
        "statusBarItem.errorBackground": "#670067c1",
        "statusBarItem.errorForeground": "#cc00ffce",
        "statusBarItem.errorHoverBackground": "#670067c8",
        "statusBarItem.errorHoverForeground": "#cc00ffce",
        "statusBarItem.focusBorder": "#05080800",
        "statusBarItem.hoverBackground": "#0e0d10fe",
        "statusBarItem.hoverForeground": "#bfb191fe",
        "statusBarItem.offlineBackground": "#0e0d10fe",
        "statusBarItem.offlineForeground": "#d0cdcec2",
        "statusBarItem.offlineHoverBackground": "#0e0d10fe",
        "statusBarItem.offlineHoverForeground": "#6d6795fe",
        "statusBarItem.prominentBackground": "#0e0d10fe",
        "statusBarItem.prominentForeground": "#c0bdbec4",
        "statusBarItem.prominentHoverBackground": "#0e0d10fe",
        "statusBarItem.prominentHoverForeground": "#7f517ffe",
        "statusBarItem.remoteBackground": "#0e0d10fe",
        "statusBarItem.remoteForeground": "#bfc0bdc3",
        "statusBarItem.remoteHoverBackground": "#0e0d10fe",
        "statusBarItem.remoteHoverForeground": "#4f6f7dfe",
        "statusBarItem.warningBackground": "#7a7a00fe",
        "statusBarItem.warningForeground": "#e6e600ce",
        "statusBarItem.warningHoverBackground": "#7a7a00fe",
        "statusBarItem.warningHoverForeground": "#e6e600ce",
        "symbolIcon.arrayForeground": "#938565fe",
        "symbolIcon.booleanForeground": "#615b89fe",
        "symbolIcon.classForeground": "#59876bfe",
        "symbolIcon.colorForeground": "#756747fe",
        "symbolIcon.constantForeground": "#bd8f96fe",
        "symbolIcon.constructorForeground": "#81535afe",
        "symbolIcon.enumeratorForeground": "#8dbb9ffe",
        "symbolIcon.enumeratorMemberForeground": "#c4ddaffe",
        "symbolIcon.eventForeground": "#85a5b3fe",
        "symbolIcon.fieldForeground": "#b4cd9ffe",
        "symbolIcon.fileForeground": "#8f89b7fe",
        "symbolIcon.folderForeground": "#817ba941",
        "symbolIcon.functionForeground": "#6b6593fe",
        "symbolIcon.interfaceForeground": "#85575efe",
        "symbolIcon.keyForeground": "#7a9365fe",
        "symbolIcon.keywordForeground": "#655f8dfe",
        "symbolIcon.methodForeground": "#5f5987fe",
        "symbolIcon.moduleForeground": "#a1737afe",
        "symbolIcon.namespaceForeground": "#436371fe",
        "symbolIcon.nullForeground": "#59876bfe",
        "symbolIcon.numberForeground": "#714371fe",
        "symbolIcon.objectForeground": "#cdbf9ffe",
        "symbolIcon.operatorForeground": "#8dadbbfe",
        "symbolIcon.packageForeground": "#789163fe",
        "symbolIcon.propertyForeground": "#638391fe",
        "symbolIcon.referenceForeground": "#774977fe",
        "symbolIcon.snippetForeground": "#9d97c5fe",
        "symbolIcon.stringForeground": "#93b3c1fe",
        "symbolIcon.structForeground": "#c2dbadfe",
        "symbolIcon.textForeground": "#8d5f66fe",
        "symbolIcon.typeParameterForeground": "#918363fe",
        "symbolIcon.unitForeground": "#bbb5e3fe",
        "symbolIcon.variableForeground": "#dbcdadfe",
        "tab.activeBackground": "#68656686",
        "tab.activeBorder": "#06050800",
        "tab.activeBorderTop": "#adcddbde",
        "tab.activeForeground": "#afcfddde",
        "tab.activeModifiedBorder": "#ffba22ce",
        "tab.border": "#08050600",
        "tab.hoverBackground": "#0e0d10fe",
        "tab.hoverBorder": "#7a797c42",
        "tab.hoverForeground": "#af8188fe",
        "tab.inactiveBackground": "#4e4d5046",
        "tab.inactiveForeground": "#68656684",
        "tab.inactiveModifiedBorder": "#ffba22ce",
        "tab.lastPinnedBorder": "#7a797c43",
        "tab.unfocusedActiveBackground": "#4e4d5025",
        "tab.unfocusedActiveBorder": "#07080500",
        "tab.unfocusedActiveBorderTop": "#90a97b41",
        "tab.unfocusedActiveForeground": "#68656682",
        "tab.unfocusedActiveModifiedBorder": "#ffba22ce",
        "tab.unfocusedHoverBackground": "#4e4d5023",
        "tab.unfocusedHoverBorder": "#4e4d5024",
        "tab.unfocusedHoverForeground": "#a8c193fe",
        "tab.unfocusedInactiveBackground": "#4e4d5025",
        "tab.unfocusedInactiveForeground": "#68656686",
        "tab.unfocusedInactiveModifiedBorder": "#ffba22ce",
        "terminal.ansiBlack": "#0c0c0ca6",
        "terminal.ansiBlue": "#4d4dffc4",
        "terminal.ansiBrightBlack": "#333333aa",
        "terminal.ansiBrightBlue": "#84a3f9b0",
        "terminal.ansiBrightCyan": "#00a5a5bf",
        "terminal.ansiBrightGreen": "#00cc00cb",
        "terminal.ansiBrightMagenta": "#cc00ffce",
        "terminal.ansiBrightRed": "#ff5050cb",
        "terminal.ansiBrightWhite": "#f4f4f4be",
        "terminal.ansiBrightYellow": "#e6e600ce",
        "terminal.ansiCyan": "#008b8ba5",
        "terminal.ansiGreen": "#004000cb",
        "terminal.ansiMagenta": "#670067c3",
        "terminal.ansiRed": "#400000cb",
        "terminal.ansiWhite": "#cececec7",
        "terminal.ansiYellow": "#7a7a00fe",
        "terminal.background": "#121114fe",
        "terminal.border": "#7a797c42",
        "terminal.dropBackground": "#121114fe",
        "terminal.findMatchBackground": "#121114fe",
        "terminal.findMatchBorder": "#7a797c41",
        "terminal.findMatchHighlightBackground": "#afa18141",
        "terminal.findMatchHighlightBorder": "#81af9341",
        "terminal.foreground": "#f4f4f4be",
        "terminal.hoverHighlightBackground": "#79a78b41",
        "terminal.inactiveSelectionBackground": "#4e4d5026",
        "terminal.selectionBackground": "#a97ba941",
        "terminal.selectionForeground": "#bdaf8fca",
        "terminal.tab.activeBorder": "#05080800",
        "terminalCommandDecoration.defaultBackground": "#437155ef",
        "terminalCommandDecoration.errorBackground": "#ff5050cb",
        "terminalCommandDecoration.successBackground": "#00cc00cb",
        "terminalCursor.background": "#121114fe",
        "terminalCursor.foreground": "#7a7a00fe",
        "terminalOverviewRuler.cursorForeground": "#a99b7b41",
        "terminalOverviewRuler.findMatchForeground": "#7999a741",
        "testing.iconErrored": "#cc00ffce",
        "testing.iconFailed": "#ff5050cb",
        "testing.iconPassed": "#00cc00cb",
        "testing.iconQueued": "#84a3f99f",
        "testing.iconSkipped": "#c0c0c0a2",
        "testing.iconUnset": "#808080ad",
        "testing.message.error.decorationForeground": "#abcbd9de",
        "testing.message.error.lineBackground": "#670067ab",
        "testing.message.info.decorationForeground": "#afcfddde",
        "testing.message.info.lineBackground": "#4d4dffaf",
        "testing.peekBorder": "#7a797c45",
        "testing.peekHeaderBackground": "#0e0d10fe",
        "testing.runAction": "#00cc00cb",
        "textBlockQuote.background": "#0e0d10fe",
        "textBlockQuote.border": "#7a797c46",
        "textCodeBlock.background": "#0e0d10fe",
        "textLink.activeForeground": "#ffba22ce",
        "textLink.foreground": "#4d4dffc7",
        "textPreformat.foreground": "#cac9ccc2",
        "textSeparator.foreground": "#cac9ccc6",
        "titleBar.activeBackground": "#060508fe",
        "titleBar.activeForeground": "#a7c7d5de",
        "titleBar.border": "#06050800",
        "titleBar.inactiveBackground": "#4e4d5023",
        "titleBar.inactiveForeground": "#68656686",
        "toolbar.activeBackground": "#7999a741",
        "toolbar.hoverBackground": "#0e0d10fe",
        "toolbar.hoverOutline": "#90a97b41",
        "tree.inactiveIndentGuidesStroke": "#7999a741",
        "tree.indentGuidesStroke": "#afcfddde",
        "tree.tableColumnsBorder": "#7a797c41",
        "tree.tableOddRowsBackground": "#0e0d10fe",
        "walkThrough.embeddedEditorBackground": "#121114fe",
        "walkthrough.stepTitle.foreground": "#d5d8d8c2",
        "welcomePage.background": "#0e0d10fe",
        "welcomePage.progress.background": "#0e0d10fe",
        "welcomePage.progress.foreground": "#d5d8d8c1",
        "welcomePage.tileBackground": "#0e0d10fe",
        "welcomePage.tileBorder": "#7a797c47",
        "welcomePage.tileHoverBackground": "#0e0d10fe",
        "widget.border": "#7a797c41",
        "widget.shadow": "#07080500",
        "window.activeBorder": "#7a797c45",
        "window.inactiveBorder": "#4e4d5025"
    },
    "tokenColors": [
        {
            "scope": "comment.block.documentation.c",
            "settings": {
                "foreground": "#6a696c9e"
            }
        },
        {
            "scope": "comment.block.html",
            "settings": {
                "foreground": "#6b6c699e"
            }
        },
        {
            "scope": "comment.block.javadoc.java",
            "settings": {
                "foreground": "#696c6c9e"
            }
        },
        {
            "scope": "comment.block.powershell",
            "settings": {
                "foreground": "#696c6c9e"
            }
        },
        {
            "scope": "comment.block.xml",
            "settings": {
                "foreground": "#696c6c9e"
            }
        },
        {
            "scope": "comment.line.double-slash.c",
            "settings": {
                "foreground": "#6a696c9e"
            }
        },
        {
            "scope": "comment.line.double-slash.cpp",
            "settings": {
                "foreground": "#6b6c699e"
            }
        },
        {
            "scope": "comment.line.double-slash.java",
            "settings": {
                "foreground": "#6c696a9e"
            }
        },
        {
            "scope": "comment.line.double-slash.js",
            "settings": {
                "foreground": "#6a696c9e"
            }
        },
        {
            "scope": "comment.line.number-sign.makefile",
            "settings": {
                "foreground": "#6b6c699e"
            }
        },
        {
            "scope": "comment.line.number-sign.python",
            "settings": {
                "foreground": "#6c696a9e"
            }
        },
        {
            "scope": "comment.line.number-sign.yaml",
            "settings": {
                "foreground": "#6c696a9e"
            }
        },
        {
            "scope": "comment.line.percentage.erlang",
            "settings": {
                "foreground": "#6b6c699e"
            }
        },
        {
            "scope": "comment.line.powershell",
            "settings": {
                "foreground": "#6a696c9e"
            }
        },
        {
            "scope": "comment.source.cmake",
            "settings": {
                "foreground": "#6a696c9e"
            }
        },
        {
            "scope": "comment.source.cmakecache",
            "settings": {
                "foreground": "#6b6c699e"
            }
        },
        {
            "scope": "constant.character",
            "settings": {
                "foreground": "#af81afe7"
            }
        },
        {
            "scope": "constant.character.character-class.regexp",
            "settings": {
                "foreground": "#635d8be6"
            }
        },
        {
            "scope": "constant.character.escape",
            "settings": {
                "foreground": "#577785e6"
            }
        },
        {
            "scope": "constant.character.set.regexp",
            "settings": {
                "foreground": "#7f9fade6"
            }
        },
        {
            "scope": "constant.language",
            "settings": {
                "foreground": "#83a3b1e7"
            }
        },
        {
            "scope": "constant.numeric",
            "settings": {
                "foreground": "#b587b5e7"
            }
        },
        {
            "scope": "constant.numeric.dec.python",
            "settings": {
                "foreground": "#6e8759e6"
            }
        },
        {
            "scope": "constant.other.caps.python",
            "settings": {
                "foreground": "#6c8557e6"
            }
        },
        {
            "scope": "constant.other.character-class.regexp",
            "settings": {
                "foreground": "#659377e6"
            }
        },
        {
            "scope": "constant.other.character-class.set.regexp",
            "settings": {
                "foreground": "#a375a3e7"
            }
        },
        {
            "scope": "constant.other.color.rgb-value",
            "settings": {
                "foreground": "#81af93e6"
            }
        },
        {
            "scope": "constant.other.placeholder",
            "settings": {
                "foreground": "#8aa375e7"
            }
        },
        {
            "scope": "constant.other.rgb-value",
            "settings": {
                "foreground": "#b3a585e6"
            }
        },
        {
            "scope": "constant.regexp",
            "settings": {
                "foreground": "#a79979e6"
            }
        },
        {
            "scope": "constant.sha.git-rebase",
            "settings": {
                "foreground": "#7b75a3e6"
            }
        },
        {
            "scope": "emphasis",
            "settings": {
                "foreground": "#afa181e7"
            }
        },
        {
            "scope": "entity.name.class",
            "settings": {
                "foreground": "#a59777e6"
            }
        },
        {
            "scope": "entity.name.function",
            "settings": {
                "foreground": "#6b997de6"
            }
        },
        {
            "scope": "entity.name.function.preprocessor",
            "settings": {
                "foreground": "#70895be7"
            }
        },
        {
            "scope": "entity.name.function.python",
            "settings": {
                "foreground": "#916391e6"
            }
        },
        {
            "scope": "entity.name.label",
            "settings": {
                "foreground": "#a97ba9e6"
            }
        },
        {
            "scope": "entity.name.namespace",
            "settings": {
                "foreground": "#ab7dabe6"
            }
        },
        {
            "scope": "entity.name.operator",
            "settings": {
                "foreground": "#857757e6"
            }
        },
        {
            "scope": "entity.name.operator.custom-literal",
            "settings": {
                "foreground": "#5f8d71e6"
            }
        },
        {
            "scope": "entity.name.scope-resolution",
            "settings": {
                "foreground": "#b3a585e6"
            }
        },
        {
            "scope": "entity.name.tag",
            "settings": {
                "foreground": "#6c8557e6"
            }
        },
        {
            "scope": "entity.name.tag.css",
            "settings": {
                "foreground": "#938565e6"
            }
        },
        {
            "scope": "entity.name.type",
            "settings": {
                "foreground": "#9b8d6de6"
            }
        },
        {
            "scope": "entity.name.variable",
            "settings": {
                "foreground": "#869f71e6"
            }
        },
        {
            "scope": "entity.other.attribute",
            "settings": {
                "foreground": "#655f8de7"
            }
        },
        {
            "scope": "entity.other.attribute-name",
            "settings": {
                "foreground": "#7e9769e6"
            }
        },
        {
            "scope": "entity.other.attribute-name.class.css",
            "settings": {
                "foreground": "#92ab7de7"
            }
        },
        {
            "scope": "entity.other.attribute-name.class.mixin.css",
            "settings": {
                "foreground": "#875960e6"
            }
        },
        {
            "scope": "entity.other.attribute-name.id",
            "settings": {
                "foreground": "#a173a1e7"
            }
        },
        {
            "scope": "entity.other.attribute-name.id.css",
            "settings": {
                "foreground": "#578569e6"
            }
        },
        {
            "scope": "entity.other.attribute-name.parent-selector.css",
            "settings": {
                "foreground": "#789163e6"
            }
        },
        {
            "scope": "entity.other.attribute-name.pseudo-class.css",
            "settings": {
                "foreground": "#857fade6"
            }
        },
        {
            "scope": "entity.other.attribute-name.pseudo-element.css",
            "settings": {
                "foreground": "#5f8d71e6"
            }
        },
        {
            "scope": "entity.other.attribute-name.scss",
            "settings": {
                "foreground": "#978969e6"
            }
        },
        {
            "scope": "entity.other.document.begin.yaml",
            "settings": {
                "foreground": "#6b6c699e"
            }
        },
        {
            "scope": "entity.other.inherited-class",
            "settings": {
                "foreground": "#87b599e6"
            }
        },
        {
            "scope": "header",
            "settings": {
                "foreground": "#79a78be7"
            }
        },
        {
            "scope": "invalid",
            "settings": {
                "foreground": "#578569e6"
            }
        },
        {
            "scope": "keyword",
            "settings": {
                "foreground": "#998b6be6"
            }
        },
        {
            "scope": "keyword.control",
            "settings": {
                "foreground": "#81af93e7"
            }
        },
        {
            "scope": "keyword.control.anchor.regexp",
            "settings": {
                "foreground": "#597987e6"
            }
        },
        {
            "scope": "keyword.control.import.python",
            "settings": {
                "foreground": "#976970e7"
            }
        },
        {
            "scope": "keyword.operator",
            "settings": {
                "foreground": "#83b195e7"
            }
        },
        {
            "scope": "keyword.operator.alignas",
            "settings": {
                "foreground": "#6d6795e6"
            }
        },
        {
            "scope": "keyword.operator.alignof",
            "settings": {
                "foreground": "#81a1afe6"
            }
        },
        {
            "scope": "keyword.operator.cast",
            "settings": {
                "foreground": "#659377e7"
            }
        },
        {
            "scope": "keyword.operator.delete",
            "settings": {
                "foreground": "#976997e7"
            }
        },
        {
            "scope": "keyword.operator.documentation.powershell",
            "settings": {
                "foreground": "#6b6c699e"
            }
        },
        {
            "scope": "keyword.operator.expression",
            "settings": {
                "foreground": "#8b5d8be7"
            }
        },
        {
            "scope": "keyword.operator.instanceof",
            "settings": {
                "foreground": "#6f6997e7"
            }
        },
        {
            "scope": "keyword.operator.logical.python",
            "settings": {
                "foreground": "#9d6f76e6"
            }
        },
        {
            "scope": "keyword.operator.minus.exponent",
            "settings": {
                "foreground": "#936593e6"
            }
        },
        {
            "scope": "keyword.operator.negation.regexp",
            "settings": {
                "foreground": "#679579e7"
            }
        },
        {
            "scope": "keyword.operator.new",
            "settings": {
                "foreground": "#6d8d9be6"
            }
        },
        {
            "scope": "keyword.operator.noexcept",
            "settings": {
                "foreground": "#ad9f7fe6"
            }
        },
        {
            "scope": "keyword.operator.or.regexp",
            "settings": {
                "foreground": "#857fade6"
            }
        },
        {
            "scope": "keyword.operator.plus.exponent",
            "settings": {
                "foreground": "#b183b1e7"
            }
        },
        {
            "scope": "keyword.operator.quantifier.regexp",
            "settings": {
                "foreground": "#afa181e6"
            }
        },
        {
            "scope": "keyword.operator.sizeof",
            "settings": {
                "foreground": "#79a78be6"
            }
        },
        {
            "scope": "keyword.operator.typeid",
            "settings": {
                "foreground": "#875987e6"
            }
        },
        {
            "scope": "keyword.operator.wordlike",
            "settings": {
                "foreground": "#638391e7"
            }
        },
        {
            "scope": "keyword.other.operator",
            "settings": {
                "foreground": "#9b6d9be7"
            }
        },
        {
            "scope": "keyword.other.package.java",
            "settings": {
                "foreground": "#71919fe6"
            }
        },
        {
            "scope": "keyword.other.unit",
            "settings": {
                "foreground": "#978969e7"
            }
        },
        {
            "scope": "keyword.other.using",
            "settings": {
                "foreground": "#7797a5e6"
            }
        },
        {
            "scope": "markup.bold",
            "settings": {
                "foreground": "#895b62e7"
            }
        },
        {
            "scope": "markup.changed",
            "settings": {
                "foreground": "#875960e6"
            }
        },
        {
            "scope": "markup.deleted",
            "settings": {
                "foreground": "#958767e6"
            }
        },
        {
            "scope": "markup.fenced_code.block.markdown",
            "settings": {
                "foreground": "#85575ee6"
            }
        },
        {
            "scope": "markup.heading",
            "settings": {
                "foreground": "#b3858ce6"
            }
        },
        {
            "scope": "markup.inline.raw",
            "settings": {
                "foreground": "#7595a3e7"
            }
        },
        {
            "scope": "markup.inserted",
            "settings": {
                "foreground": "#7a9365e7"
            }
        },
        {
            "scope": "markup.italic",
            "settings": {
                "foreground": "#77719fe6"
            }
        },
        {
            "scope": "markup.raw.block.markdown",
            "settings": {
                "foreground": "#7f79a7e7"
            }
        },
        {
            "scope": "markup.strikethrough",
            "settings": {
                "foreground": "#a577a5e6"
            }
        },
        {
            "scope": "markup.underline",
            "settings": {
                "foreground": "#938565e6"
            }
        },
        {
            "scope": "meta.block.c",
            "settings": {
                "foreground": "#996b99e7"
            }
        },
        {
            "scope": "meta.class.java",
            "settings": {
                "foreground": "#7999a7e6"
            }
        },
        {
            "scope": "meta.definition.variable.name",
            "settings": {
                "foreground": "#ab7dabe7"
            }
        },
        {
            "scope": "meta.diff.header",
            "settings": {
                "foreground": "#b5878ee6"
            }
        },
        {
            "scope": "meta.embedded",
            "settings": {
                "foreground": "#85b397e7"
            }
        },
        {
            "scope": "meta.embedded.assembly",
            "settings": {
                "foreground": "#698997e6"
            }
        },
        {
            "scope": "meta.function-call.arguments.python",
            "settings": {
                "foreground": "#ad7f86e7"
            }
        },
        {
            "scope": "meta.function-call.python",
            "settings": {
                "foreground": "#9f719fe7"
            }
        },
        {
            "scope": "meta.member.access.python",
            "settings": {
                "foreground": "#875960e6"
            }
        },
        {
            "scope": "meta.method.java",
            "settings": {
                "foreground": "#a375a3e6"
            }
        },
        {
            "scope": "meta.object-literal.key",
            "settings": {
                "foreground": "#638391e6"
            }
        },
        {
            "scope": "meta.paragraph.markdown",
            "settings": {
                "foreground": "#a19373e6"
            }
        },
        {
            "scope": "meta.preprocessor",
            "settings": {
                "foreground": "#a77980e7"
            }
        },
        {
            "scope": "meta.preprocessor.numeric",
            "settings": {
                "foreground": "#6b997de7"
            }
        },
        {
            "scope": "meta.preprocessor.string",
            "settings": {
                "foreground": "#71919fe6"
            }
        },
        {
            "scope": "meta.structure.dictionary.json.comments",
            "settings": {
                "foreground": "#6c696a9e"
            }
        },
        {
            "scope": "meta.structure.dictionary.key.python",
            "settings": {
                "foreground": "#81af93e6"
            }
        },
        {
            "scope": "meta.structure.dictionary.value.json.comments",
            "settings": {
                "foreground": "#6b6c699e"
            }
        },
        {
            "scope": "meta.template.expression",
            "settings": {
                "foreground": "#9f7178e7"
            }
        },
        {
            "scope": "meta.type.cast.expr",
            "settings": {
                "foreground": "#8ca577e7"
            }
        },
        {
            "scope": "meta.type.new.expr",
            "settings": {
                "foreground": "#b1838ae6"
            }
        },
        {
            "scope": "parameter",
            "settings": {
                "foreground": "#79a78be6"
            }
        },
        {
            "scope": "punctuation.character.set.begin.regexp",
            "settings": {
                "foreground": "#696c6c9e"
            }
        },
        {
            "scope": "punctuation.character.set.end.regexp",
            "settings": {
                "foreground": "#696c6c9e"
            }
        },
        {
            "scope": "punctuation.definition.character-class.regexp",
            "settings": {
                "foreground": "#6b6c699e"
            }
        },
        {
            "scope": "punctuation.definition.comment",
            "settings": {
                "foreground": "#6a696c9e"
            }
        },
        {
            "scope": "punctuation.definition.comment.json.comments",
            "settings": {
                "foreground": "#6a696c9e"
            }
        },
        {
            "scope": "punctuation.definition.comment.python",
            "settings": {
                "foreground": "#6c696a9e"
            }
        },
        {
            "scope": "punctuation.definition.dictionary.end.json",
            "settings": {
                "foreground": "#696c6c9e"
            }
        },
        {
            "scope": "punctuation.definition.group.assertion.regexp",
            "settings": {
                "foreground": "#6c696a9e"
            }
        },
        {
            "scope": "punctuation.definition.group.regexp",
            "settings": {
                "foreground": "#6c696a9e"
            }
        },
        {
            "scope": "punctuation.definition.list.begin.markdown",
            "settings": {
                "foreground": "#6c696a9e"
            }
        },
        {
            "scope": "punctuation.definition.parameters.begin.python",
            "settings": {
                "foreground": "#696c6c9e"
            }
        },
        {
            "scope": "punctuation.definition.quote.begin.markdown",
            "settings": {
                "foreground": "#6a696c9e"
            }
        },
        {
            "scope": "punctuation.definition.tag",
            "settings": {
                "foreground": "#6b6c699e"
            }
        },
        {
            "scope": "punctuation.definition.template-expression.begin",
            "settings": {
                "foreground": "#6a696c9e"
            }
        },
        {
            "scope": "punctuation.definition.template-expression.end",
            "settings": {
                "foreground": "#6b6c699e"
            }
        },
        {
            "scope": "punctuation.section.embedded",
            "settings": {
                "foreground": "#6b6c699e"
            }
        },
        {
            "scope": "punctuation.section.embedded.begin.php",
            "settings": {
                "foreground": "#6b6c699e"
            }
        },
        {
            "scope": "punctuation.section.embedded.end.php",
            "settings": {
                "foreground": "#6a696c9e"
            }
        },
        {
            "scope": "punctuation.terminator.java",
            "settings": {
                "foreground": "#696c6c9e"
            }
        },
        {
            "scope": "source.cmake",
            "settings": {
                "foreground": "#7b9ba9e6"
            }
        },
        {
            "scope": "source.coffee.embedded",
            "settings": {
                "foreground": "#9b6d74e6"
            }
        },
        {
            "scope": "source.cpp",
            "settings": {
                "foreground": "#9d6f9de7"
            }
        },
        {
            "scope": "source.css.less",
            "settings": {
                "foreground": "#577785e6"
            }
        },
        {
            "scope": "source.groovy.embedded",
            "settings": {
                "foreground": "#679579e6"
            }
        },
        {
            "scope": "source.java",
            "settings": {
                "foreground": "#94ad7fe7"
            }
        },
        {
            "scope": "source.java-properties",
            "settings": {
                "foreground": "#9b8d6de7"
            }
        },
        {
            "scope": "source.json.comments",
            "settings": {
                "foreground": "#6b6c699e"
            }
        },
        {
            "scope": "source.powershell",
            "settings": {
                "foreground": "#5b896de6"
            }
        },
        {
            "scope": "source.powershell.variable.other.member",
            "settings": {
                "foreground": "#978969e7"
            }
        },
        {
            "scope": "source.python",
            "settings": {
                "foreground": "#698997e6"
            }
        },
        {
            "scope": "storage",
            "settings": {
                "foreground": "#618f73e6"
            }
        },
        {
            "scope": "storage.modifier",
            "settings": {
                "foreground": "#748d5fe7"
            }
        },
        {
            "scope": "storage.modifier.import.java",
            "settings": {
                "foreground": "#996b99e7"
            }
        },
        {
            "scope": "storage.modifier.package.java",
            "settings": {
                "foreground": "#5d5785e6"
            }
        },
        {
            "scope": "storage.type",
            "settings": {
                "foreground": "#855785e7"
            }
        },
        {
            "scope": "storage.type.annotation.groovy",
            "settings": {
                "foreground": "#6d6795e6"
            }
        },
        {
            "scope": "storage.type.annotation.java",
            "settings": {
                "foreground": "#916391e7"
            }
        },
        {
            "scope": "storage.type.boolean.go",
            "settings": {
                "foreground": "#b183b1e6"
            }
        },
        {
            "scope": "storage.type.byte.go",
            "settings": {
                "foreground": "#81a1afe6"
            }
        },
        {
            "scope": "storage.type.cs",
            "settings": {
                "foreground": "#80996be7"
            }
        },
        {
            "scope": "storage.type.error.go",
            "settings": {
                "foreground": "#869f71e7"
            }
        },
        {
            "scope": "storage.type.generic.cs",
            "settings": {
                "foreground": "#837dabe7"
            }
        },
        {
            "scope": "storage.type.generic.groovy",
            "settings": {
                "foreground": "#748d5fe7"
            }
        },
        {
            "scope": "storage.type.generic.java",
            "settings": {
                "foreground": "#8b5d64e7"
            }
        },
        {
            "scope": "storage.type.groovy",
            "settings": {
                "foreground": "#678795e7"
            }
        },
        {
            "scope": "storage.type.java",
            "settings": {
                "foreground": "#716b99e7"
            }
        },
        {
            "scope": "storage.type.modifier.cs",
            "settings": {
                "foreground": "#a5777ee7"
            }
        },
        {
            "scope": "storage.type.numeric.go",
            "settings": {
                "foreground": "#719f83e6"
            }
        },
        {
            "scope": "storage.type.object.array.groovy",
            "settings": {
                "foreground": "#5d7d8be7"
            }
        },
        {
            "scope": "storage.type.object.array.java",
            "settings": {
                "foreground": "#938565e7"
            }
        },
        {
            "scope": "storage.type.parameters.groovy",
            "settings": {
                "foreground": "#a59777e7"
            }
        },
        {
            "scope": "storage.type.primitive.array.groovy",
            "settings": {
                "foreground": "#639175e6"
            }
        },
        {
            "scope": "storage.type.primitive.array.java",
            "settings": {
                "foreground": "#7b9ba9e7"
            }
        },
        {
            "scope": "storage.type.primitive.groovy",
            "settings": {
                "foreground": "#615b89e6"
            }
        },
        {
            "scope": "storage.type.primitive.java",
            "settings": {
                "foreground": "#998b6be6"
            }
        },
        {
            "scope": "storage.type.rune.go",
            "settings": {
                "foreground": "#8f6168e7"
            }
        },
        {
            "scope": "storage.type.string.go",
            "settings": {
                "foreground": "#8d7f5fe6"
            }
        },
        {
            "scope": "storage.type.token.java",
            "settings": {
                "foreground": "#ab7d84e6"
            }
        },
        {
            "scope": "storage.type.uintptr.go",
            "settings": {
                "foreground": "#61818fe6"
            }
        },
        {
            "scope": "storage.type.variable.cs",
            "settings": {
                "foreground": "#b385b3e7"
            }
        },
        {
            "scope": "string",
            "settings": {
                "foreground": "#996b72e7"
            }
        },
        {
            "scope": "string.quoted.docstring.multi.python",
            "settings": {
                "foreground": "#6b6c699e"
            }
        },
        {
            "scope": "string.regexp",
            "settings": {
                "foreground": "#658593e7"
            }
        },
        {
            "scope": "string.tag",
            "settings": {
                "foreground": "#5f8d71e6"
            }
        },
        {
            "scope": "string.value",
            "settings": {
                "foreground": "#7d77a5e7"
            }
        },
        {
            "scope": "strong",
            "settings": {
                "foreground": "#659377e6"
            }
        },
        {
            "scope": "support.class",
            "settings": {
                "foreground": "#938565e7"
            }
        },
        {
            "scope": "support.constant.color",
            "settings": {
                "foreground": "#75a387e6"
            }
        },
        {
            "scope": "support.constant.dom",
            "settings": {
                "foreground": "#85a5b3e6"
            }
        },
        {
            "scope": "support.constant.font-name",
            "settings": {
                "foreground": "#638391e6"
            }
        },
        {
            "scope": "support.constant.handlebars",
            "settings": {
                "foreground": "#a79979e7"
            }
        },
        {
            "scope": "support.constant.json",
            "settings": {
                "foreground": "#7f9fade7"
            }
        },
        {
            "scope": "support.constant.math",
            "settings": {
                "foreground": "#8ca577e6"
            }
        },
        {
            "scope": "support.constant.media",
            "settings": {
                "foreground": "#789163e7"
            }
        },
        {
            "scope": "support.constant.media-type",
            "settings": {
                "foreground": "#875960e6"
            }
        },
        {
            "scope": "support.constant.property-value",
            "settings": {
                "foreground": "#91636ae6"
            }
        },
        {
            "scope": "support.function",
            "settings": {
                "foreground": "#ab9d7de6"
            }
        },
        {
            "scope": "support.function.git-rebase",
            "settings": {
                "foreground": "#976997e7"
            }
        },
        {
            "scope": "support.other.parenthesis.regexp",
            "settings": {
                "foreground": "#7d9dabe7"
            }
        },
        {
            "scope": "support.type",
            "settings": {
                "foreground": "#af8188e6"
            }
        },
        {
            "scope": "support.type.property-name",
            "settings": {
                "foreground": "#719f83e7"
            }
        },
        {
            "scope": "support.type.vendored.property-name",
            "settings": {
                "foreground": "#6b8b99e6"
            }
        },
        {
            "scope": "support.variable",
            "settings": {
                "foreground": "#5f7f8de6"
            }
        },
        {
            "scope": "token.debug-token",
            "settings": {
                "foreground": "#5b7b89e6"
            }
        },
        {
            "scope": "token.error-token",
            "settings": {
                "foreground": "#7f79a7e6"
            }
        },
        {
            "scope": "token.info-token",
            "settings": {
                "foreground": "#618f73e6"
            }
        },
        {
            "scope": "token.warn-token",
            "settings": {
                "foreground": "#85a5b3e7"
            }
        },
        {
            "scope": "variable",
            "settings": {
                "foreground": "#87a7b5e6"
            }
        },
        {
            "scope": "variable.css",
            "settings": {
                "foreground": "#849d6fe7"
            }
        },
        {
            "scope": "variable.language",
            "settings": {
                "foreground": "#b587b5e6"
            }
        },
        {
            "scope": "variable.language.wildcard.java",
            "settings": {
                "foreground": "#a19373e7"
            }
        },
        {
            "scope": "variable.other.constant",
            "settings": {
                "foreground": "#6c8557e7"
            }
        },
        {
            "scope": "variable.other.definition.java",
            "settings": {
                "foreground": "#85575ee7"
            }
        },
        {
            "scope": "variable.other.enummember",
            "settings": {
                "foreground": "#9f7178e7"
            }
        },
        {
            "scope": "variable.other.less",
            "settings": {
                "foreground": "#635d8be7"
            }
        },
        {
            "scope": "variable.other.object.java",
            "settings": {
                "foreground": "#768f61e6"
            }
        },
        {
            "scope": "variable.other.object.property.java",
            "settings": {
                "foreground": "#a577a5e7"
            }
        },
        {
            "scope": "variable.parameter.c",
            "settings": {
                "foreground": "#81af93e6"
            }
        },
        {
            "scope": "variable.parameter.function.language.python",
            "settings": {
                "foreground": "#6b8b99e6"
            }
        },
        {
            "scope": "variable.parameter.java",
            "settings": {
                "foreground": "#ab7d84e7"
            }
        },
        {
            "scope": "variable.scss",
            "settings": {
                "foreground": "#869f71e6"
            }
        }
    ]
}